{"TrainCount": 1, "MeanTrainLoss": 0.12499964045693508, "MeanValidationLoss": 0.08468643550546796, "FinalMeanRMSE": -1}
{"TrainCount": 1, "MeanTrainLoss": 0.11747859773404172, "MeanValidationLoss": 0.07706196522646247, "FinalMeanRMSE": -1}
{"TrainCount": 1, "MeanTrainLoss": 0.1067283212975088, "MeanValidationLoss": 0.06832693024875133, "FinalMeanRMSE": -1}
{"TrainCount": 1, "MeanTrainLoss": 0.09514779149084629, "MeanValidationLoss": 0.06029681168811422, "FinalMeanRMSE": -1}
{"TrainCount": 1, "MeanTrainLoss": 0.08455948670596164, "MeanValidationLoss": 0.05368293835803377, "FinalMeanRMSE": -1}
{"TrainCount": 1, "MeanTrainLoss": 0.07624179602463417, "MeanValidationLoss": 0.048832348429820906, "FinalMeanRMSE": -1}
{"TrainCount": 1, "MeanTrainLoss": 0.0707828098540209, "MeanValidationLoss": 0.04554478706958148, "FinalMeanRMSE": -1}
{"TrainCount": 1, "MeanTrainLoss": 0.06756245850535769, "MeanValidationLoss": 0.043305808669524576, "FinalMeanRMSE": -1}
{"TrainCount": 1, "MeanTrainLoss": 0.06566972239964808, "MeanValidationLoss": 0.04180331673350692, "FinalMeanRMSE": -1}
{"TrainCount": 1, "MeanTrainLoss": 0.06497671265960861, "MeanValidationLoss": 0.0399233577816699, "FinalMeanRMSE": -1}
{"TrainCount": 1, "MeanTrainLoss": 0.06345695909988544, "MeanValidationLoss": 0.039869298572551476, "FinalMeanRMSE": -1}
{"TrainCount": 1, "MeanTrainLoss": 0.0633260951403727, "MeanValidationLoss": 0.03982454545341187, "FinalMeanRMSE": -1}
{"TrainCount": 1, "MeanTrainLoss": 0.0632716793928961, "MeanValidationLoss": 0.03976921247484538, "FinalMeanRMSE": -1}
{"TrainCount": 1, "MeanTrainLoss": 0.06324401769938888, "MeanValidationLoss": 0.039726578958437474, "FinalMeanRMSE": -1}
{"TrainCount": 1, "MeanTrainLoss": 0.06323164181789634, "MeanValidationLoss": 0.03969694817429977, "FinalMeanRMSE": 0.1992409284921052}
{"TrainCount": 2, "MeanTrainLoss": 0.04016718892774112, "MeanValidationLoss": 0.04632437404580217, "FinalMeanRMSE": -1}
{"TrainCount": 2, "MeanTrainLoss": 0.03966469517056371, "MeanValidationLoss": 0.04733630866994933, "FinalMeanRMSE": -1}
{"TrainCount": 2, "MeanTrainLoss": 0.039568510614860226, "MeanValidationLoss": 0.047914922434501545, "FinalMeanRMSE": -1}
{"TrainCount": 2, "MeanTrainLoss": 0.0395281370729208, "MeanValidationLoss": 0.048513693271806, "FinalMeanRMSE": -1}
{"TrainCount": 2, "MeanTrainLoss": 0.03950508411081744, "MeanValidationLoss": 0.04871798346124629, "FinalMeanRMSE": -1}
{"TrainCount": 2, "MeanTrainLoss": 0.03949037632367141, "MeanValidationLoss": 0.04888464275885512, "FinalMeanRMSE": -1}
{"TrainCount": 2, "MeanTrainLoss": 0.03948518080295811, "MeanValidationLoss": 0.049017427952358965, "FinalMeanRMSE": -1}
{"TrainCount": 2, "MeanTrainLoss": 0.039480969047462434, "MeanValidationLoss": 0.04912566007287414, "FinalMeanRMSE": -1}
{"TrainCount": 2, "MeanTrainLoss": 0.03947875827131137, "MeanValidationLoss": 0.04921179806823453, "FinalMeanRMSE": -1}
{"TrainCount": 2, "MeanTrainLoss": 0.039476827154277076, "MeanValidationLoss": 0.049281342280289485, "FinalMeanRMSE": -1}
{"TrainCount": 2, "MeanTrainLoss": 0.039475680892946015, "MeanValidationLoss": 0.0493358334615117, "FinalMeanRMSE": -1}
{"TrainCount": 2, "MeanTrainLoss": 0.03947439915697339, "MeanValidationLoss": 0.04937929794113472, "FinalMeanRMSE": -1}
{"TrainCount": 2, "MeanTrainLoss": 0.03947333668843961, "MeanValidationLoss": 0.049413522301369875, "FinalMeanRMSE": -1}
{"TrainCount": 2, "MeanTrainLoss": 0.039472194257336606, "MeanValidationLoss": 0.04944070588265147, "FinalMeanRMSE": -1}
{"TrainCount": 2, "MeanTrainLoss": 0.03947108422576542, "MeanValidationLoss": 0.04946214861418835, "FinalMeanRMSE": 0.22240087531449038}
{"TrainCount": 3, "MeanTrainLoss": 0.03880148065602121, "MeanValidationLoss": 0.05447098719222205, "FinalMeanRMSE": -1}
{"TrainCount": 3, "MeanTrainLoss": 0.03828548555450937, "MeanValidationLoss": 0.054386137765810784, "FinalMeanRMSE": -1}
{"TrainCount": 3, "MeanTrainLoss": 0.0383070729261527, "MeanValidationLoss": 0.05435934283422984, "FinalMeanRMSE": -1}
{"TrainCount": 3, "MeanTrainLoss": 0.038308564893489966, "MeanValidationLoss": 0.05434480608196302, "FinalMeanRMSE": -1}
{"TrainCount": 3, "MeanTrainLoss": 0.038298391079975784, "MeanValidationLoss": 0.05433848723425843, "FinalMeanRMSE": -1}
{"TrainCount": 3, "MeanTrainLoss": 0.03828786137553812, "MeanValidationLoss": 0.054330729085454194, "FinalMeanRMSE": -1}
{"TrainCount": 3, "MeanTrainLoss": 0.038272425463777376, "MeanValidationLoss": 0.05433853420381722, "FinalMeanRMSE": -1}
{"TrainCount": 3, "MeanTrainLoss": 0.03825952738889156, "MeanValidationLoss": 0.05435013704104907, "FinalMeanRMSE": -1}
{"TrainCount": 3, "MeanTrainLoss": 0.038247510196606806, "MeanValidationLoss": 0.05436441170111779, "FinalMeanRMSE": -1}
{"TrainCount": 3, "MeanTrainLoss": 0.03823653642842375, "MeanValidationLoss": 0.054380364389875514, "FinalMeanRMSE": -1}
{"TrainCount": 3, "MeanTrainLoss": 0.03822656819151223, "MeanValidationLoss": 0.05439721288219575, "FinalMeanRMSE": -1}
{"TrainCount": 3, "MeanTrainLoss": 0.038217526294885236, "MeanValidationLoss": 0.05441436756934438, "FinalMeanRMSE": -1}
{"TrainCount": 3, "MeanTrainLoss": 0.0382093260396112, "MeanValidationLoss": 0.05443137822337964, "FinalMeanRMSE": -1}
{"TrainCount": 3, "MeanTrainLoss": 0.03820188773190317, "MeanValidationLoss": 0.05444792591138369, "FinalMeanRMSE": -1}
{"TrainCount": 3, "MeanTrainLoss": 0.03819525161860911, "MeanValidationLoss": 0.05446355269732563, "FinalMeanRMSE": 0.23337427717768106}
{"TrainCount": 4, "MeanTrainLoss": 0.044285094156861306, "MeanValidationLoss": 0.046600967690528156, "FinalMeanRMSE": -1}
{"TrainCount": 4, "MeanTrainLoss": 0.04415340847180536, "MeanValidationLoss": 0.0465676208142655, "FinalMeanRMSE": -1}
{"TrainCount": 4, "MeanTrainLoss": 0.04407137355037655, "MeanValidationLoss": 0.04654572055820959, "FinalMeanRMSE": -1}
{"TrainCount": 4, "MeanTrainLoss": 0.044008291348659745, "MeanValidationLoss": 0.046531169200278666, "FinalMeanRMSE": -1}
{"TrainCount": 4, "MeanTrainLoss": 0.04395859376573935, "MeanValidationLoss": 0.04652177131768451, "FinalMeanRMSE": -1}
{"TrainCount": 4, "MeanTrainLoss": 0.043918367248804616, "MeanValidationLoss": 0.046515756305381954, "FinalMeanRMSE": -1}
{"TrainCount": 4, "MeanTrainLoss": 0.043885004306832946, "MeanValidationLoss": 0.04651192895858642, "FinalMeanRMSE": -1}
{"TrainCount": 4, "MeanTrainLoss": 0.04386633187998086, "MeanValidationLoss": 0.04675315854599677, "FinalMeanRMSE": -1}
{"TrainCount": 4, "MeanTrainLoss": 0.043866953225495914, "MeanValidationLoss": 0.04666312822107091, "FinalMeanRMSE": -1}
{"TrainCount": 4, "MeanTrainLoss": 0.04382949048249672, "MeanValidationLoss": 0.04661626639555257, "FinalMeanRMSE": -1}
{"TrainCount": 4, "MeanTrainLoss": 0.04380240548557291, "MeanValidationLoss": 0.04658596109913056, "FinalMeanRMSE": -1}
{"TrainCount": 4, "MeanTrainLoss": 0.04377999554015696, "MeanValidationLoss": 0.046566042921928515, "FinalMeanRMSE": -1}
{"TrainCount": 4, "MeanTrainLoss": 0.04376082791450123, "MeanValidationLoss": 0.04655288439618057, "FinalMeanRMSE": -1}
{"TrainCount": 4, "MeanTrainLoss": 0.04379339478847881, "MeanValidationLoss": 0.04669111269155899, "FinalMeanRMSE": -1}
{"TrainCount": 4, "MeanTrainLoss": 0.0437501744578282, "MeanValidationLoss": 0.04663391896041043, "FinalMeanRMSE": 0.21594888029661985}
{"TrainCount": 5, "MeanTrainLoss": 0.03174553761879603, "MeanValidationLoss": 0.04716654844008959, "FinalMeanRMSE": -1}
{"TrainCount": 5, "MeanTrainLoss": 0.03160072659166195, "MeanValidationLoss": 0.046954989949098, "FinalMeanRMSE": -1}
{"TrainCount": 5, "MeanTrainLoss": 0.03150937439372333, "MeanValidationLoss": 0.046822443088659876, "FinalMeanRMSE": -1}
{"TrainCount": 5, "MeanTrainLoss": 0.03144955675069911, "MeanValidationLoss": 0.04673554473198377, "FinalMeanRMSE": -1}
{"TrainCount": 5, "MeanTrainLoss": 0.03140809360342339, "MeanValidationLoss": 0.04667576207564427, "FinalMeanRMSE": -1}
{"TrainCount": 5, "MeanTrainLoss": 0.03137736493387283, "MeanValidationLoss": 0.04663243373999229, "FinalMeanRMSE": -1}
{"TrainCount": 5, "MeanTrainLoss": 0.031353087960861815, "MeanValidationLoss": 0.04659933132620958, "FinalMeanRMSE": -1}
{"TrainCount": 5, "MeanTrainLoss": 0.03133287152920205, "MeanValidationLoss": 0.046572769834445076, "FinalMeanRMSE": -1}
{"TrainCount": 5, "MeanTrainLoss": 0.031315671116447986, "MeanValidationLoss": 0.04655063874446429, "FinalMeanRMSE": -1}
{"TrainCount": 5, "MeanTrainLoss": 0.031300129698446165, "MeanValidationLoss": 0.04653144983144907, "FinalMeanRMSE": -1}
{"TrainCount": 5, "MeanTrainLoss": 0.03128580527547269, "MeanValidationLoss": 0.046514382098729795, "FinalMeanRMSE": -1}
{"TrainCount": 5, "MeanTrainLoss": 0.031272727352543134, "MeanValidationLoss": 0.04649901791260792, "FinalMeanRMSE": -1}
{"TrainCount": 5, "MeanTrainLoss": 0.031260663910936085, "MeanValidationLoss": 0.04648500262544705, "FinalMeanRMSE": -1}
{"TrainCount": 5, "MeanTrainLoss": 0.03124953300739901, "MeanValidationLoss": 0.04647270595798125, "FinalMeanRMSE": -1}
{"TrainCount": 5, "MeanTrainLoss": 0.031239297175302338, "MeanValidationLoss": 0.04646062272099348, "FinalMeanRMSE": 0.21554726067489324}
{"TrainCount": 6, "MeanTrainLoss": 0.03549995951870658, "MeanValidationLoss": 0.04381951884083126, "FinalMeanRMSE": -1}
{"TrainCount": 6, "MeanTrainLoss": 0.03534587763968002, "MeanValidationLoss": 0.04390170781508736, "FinalMeanRMSE": -1}
{"TrainCount": 6, "MeanTrainLoss": 0.035305868077978315, "MeanValidationLoss": 0.043942354187585304, "FinalMeanRMSE": -1}
{"TrainCount": 6, "MeanTrainLoss": 0.035285092794886196, "MeanValidationLoss": 0.04397042246832364, "FinalMeanRMSE": -1}
{"TrainCount": 6, "MeanTrainLoss": 0.0352723235926445, "MeanValidationLoss": 0.04399213443199793, "FinalMeanRMSE": -1}
{"TrainCount": 6, "MeanTrainLoss": 0.03526402533907129, "MeanValidationLoss": 0.0440090157199597, "FinalMeanRMSE": -1}
{"TrainCount": 6, "MeanTrainLoss": 0.03525847770520542, "MeanValidationLoss": 0.04402201309584189, "FinalMeanRMSE": -1}
{"TrainCount": 6, "MeanTrainLoss": 0.03525464815951614, "MeanValidationLoss": 0.044031956273576485, "FinalMeanRMSE": -1}
{"TrainCount": 6, "MeanTrainLoss": 0.035251863972923486, "MeanValidationLoss": 0.044039554678011635, "FinalMeanRMSE": -1}
{"TrainCount": 6, "MeanTrainLoss": 0.035249843542654834, "MeanValidationLoss": 0.04404532866201539, "FinalMeanRMSE": -1}
{"TrainCount": 6, "MeanTrainLoss": 0.035248256189726206, "MeanValidationLoss": 0.04404976596866829, "FinalMeanRMSE": -1}
{"TrainCount": 6, "MeanTrainLoss": 0.035247026465788305, "MeanValidationLoss": 0.044053108687850014, "FinalMeanRMSE": -1}
{"TrainCount": 6, "MeanTrainLoss": 0.035246127129094786, "MeanValidationLoss": 0.044055625796318054, "FinalMeanRMSE": -1}
{"TrainCount": 6, "MeanTrainLoss": 0.03524544204933098, "MeanValidationLoss": 0.04405755700840466, "FinalMeanRMSE": -1}
{"TrainCount": 6, "MeanTrainLoss": 0.03524488704615688, "MeanValidationLoss": 0.04405907239171042, "FinalMeanRMSE": 0.20990253345967225}
{"TrainCount": 7, "MeanTrainLoss": 0.04261458803451958, "MeanValidationLoss": 0.04474747798418346, "FinalMeanRMSE": -1}
{"TrainCount": 7, "MeanTrainLoss": 0.04256273281669291, "MeanValidationLoss": 0.04476159999835981, "FinalMeanRMSE": -1}
{"TrainCount": 7, "MeanTrainLoss": 0.04254293331456347, "MeanValidationLoss": 0.044787714997791266, "FinalMeanRMSE": -1}
{"TrainCount": 7, "MeanTrainLoss": 0.042532885816279196, "MeanValidationLoss": 0.04481250364078234, "FinalMeanRMSE": -1}
{"TrainCount": 7, "MeanTrainLoss": 0.0425269395656086, "MeanValidationLoss": 0.04483285056401606, "FinalMeanRMSE": -1}
{"TrainCount": 7, "MeanTrainLoss": 0.04252320722356472, "MeanValidationLoss": 0.04484924959809813, "FinalMeanRMSE": -1}
{"TrainCount": 7, "MeanTrainLoss": 0.04252073644811037, "MeanValidationLoss": 0.044862378235549144, "FinalMeanRMSE": -1}
{"TrainCount": 7, "MeanTrainLoss": 0.04251900806615727, "MeanValidationLoss": 0.04487286528495893, "FinalMeanRMSE": -1}
{"TrainCount": 7, "MeanTrainLoss": 0.04251773003700925, "MeanValidationLoss": 0.0448812723976292, "FinalMeanRMSE": -1}
{"TrainCount": 7, "MeanTrainLoss": 0.04251673089548232, "MeanValidationLoss": 0.04488806033583537, "FinalMeanRMSE": -1}
{"TrainCount": 7, "MeanTrainLoss": 0.04251591281664127, "MeanValidationLoss": 0.044893598107442464, "FinalMeanRMSE": -1}
{"TrainCount": 7, "MeanTrainLoss": 0.04251521517753873, "MeanValidationLoss": 0.044898172917023096, "FinalMeanRMSE": -1}
{"TrainCount": 7, "MeanTrainLoss": 0.04251460507851527, "MeanValidationLoss": 0.044902023795532854, "FinalMeanRMSE": -1}
{"TrainCount": 7, "MeanTrainLoss": 0.04251406830576395, "MeanValidationLoss": 0.044905316799062574, "FinalMeanRMSE": -1}
{"TrainCount": 7, "MeanTrainLoss": 0.04251359111219984, "MeanValidationLoss": 0.04490814551915208, "FinalMeanRMSE": 0.2119154211770494}
{"TrainCount": 8, "MeanTrainLoss": 0.0390564094375726, "MeanValidationLoss": 0.044577520264395265, "FinalMeanRMSE": -1}
{"TrainCount": 8, "MeanTrainLoss": 0.038905398594954656, "MeanValidationLoss": 0.0446540538615741, "FinalMeanRMSE": -1}
{"TrainCount": 8, "MeanTrainLoss": 0.03889845391046974, "MeanValidationLoss": 0.04472939718400252, "FinalMeanRMSE": -1}
{"TrainCount": 8, "MeanTrainLoss": 0.03889730714616321, "MeanValidationLoss": 0.04478498951312625, "FinalMeanRMSE": -1}
{"TrainCount": 8, "MeanTrainLoss": 0.03889734279406584, "MeanValidationLoss": 0.04482439728676255, "FinalMeanRMSE": -1}
{"TrainCount": 8, "MeanTrainLoss": 0.03889764112139505, "MeanValidationLoss": 0.044851961726824985, "FinalMeanRMSE": -1}
{"TrainCount": 8, "MeanTrainLoss": 0.038897849703862286, "MeanValidationLoss": 0.044871096241799635, "FinalMeanRMSE": -1}
{"TrainCount": 8, "MeanTrainLoss": 0.038897868625971735, "MeanValidationLoss": 0.04488431569506691, "FinalMeanRMSE": -1}
{"TrainCount": 8, "MeanTrainLoss": 0.03889769329235397, "MeanValidationLoss": 0.044893417672695966, "FinalMeanRMSE": -1}
{"TrainCount": 8, "MeanTrainLoss": 0.03889736310154402, "MeanValidationLoss": 0.044899675918825654, "FinalMeanRMSE": -1}
{"TrainCount": 8, "MeanTrainLoss": 0.03889692187849897, "MeanValidationLoss": 0.044903982036553144, "FinalMeanRMSE": -1}
{"TrainCount": 8, "MeanTrainLoss": 0.0388964047980687, "MeanValidationLoss": 0.04490695511064025, "FinalMeanRMSE": -1}
{"TrainCount": 8, "MeanTrainLoss": 0.03889584537941853, "MeanValidationLoss": 0.044909024604758305, "FinalMeanRMSE": -1}
{"TrainCount": 8, "MeanTrainLoss": 0.038895260601762745, "MeanValidationLoss": 0.044910481650979855, "FinalMeanRMSE": -1}
{"TrainCount": 8, "MeanTrainLoss": 0.038894671245632256, "MeanValidationLoss": 0.044911530758842265, "FinalMeanRMSE": 0.21192340731775575}
{"TrainCount": 9, "MeanTrainLoss": 0.0350861351048529, "MeanValidationLoss": 0.04379423874381341, "FinalMeanRMSE": -1}
{"TrainCount": 9, "MeanTrainLoss": 0.03462397279442009, "MeanValidationLoss": 0.04345319871055452, "FinalMeanRMSE": -1}
{"TrainCount": 9, "MeanTrainLoss": 0.03430467344315099, "MeanValidationLoss": 0.043318966109501686, "FinalMeanRMSE": -1}
{"TrainCount": 9, "MeanTrainLoss": 0.03413944525941717, "MeanValidationLoss": 0.04325015313531223, "FinalMeanRMSE": -1}
{"TrainCount": 9, "MeanTrainLoss": 0.034030270018906246, "MeanValidationLoss": 0.04321977035387566, "FinalMeanRMSE": -1}
{"TrainCount": 9, "MeanTrainLoss": 0.03404297717975318, "MeanValidationLoss": 0.0432981167380747, "FinalMeanRMSE": -1}
{"TrainCount": 9, "MeanTrainLoss": 0.03407050547734131, "MeanValidationLoss": 0.04321976937353611, "FinalMeanRMSE": -1}
{"TrainCount": 9, "MeanTrainLoss": 0.03410964074424372, "MeanValidationLoss": 0.04323227742784902, "FinalMeanRMSE": -1}
{"TrainCount": 9, "MeanTrainLoss": 0.034166421985795774, "MeanValidationLoss": 0.04324427546050988, "FinalMeanRMSE": -1}
{"TrainCount": 9, "MeanTrainLoss": 0.03398595866084882, "MeanValidationLoss": 0.04320310840481206, "FinalMeanRMSE": -1}
{"TrainCount": 9, "MeanTrainLoss": 0.033903598402274256, "MeanValidationLoss": 0.04336975372739529, "FinalMeanRMSE": -1}
{"TrainCount": 9, "MeanTrainLoss": 0.03387416112572933, "MeanValidationLoss": 0.043323512336141186, "FinalMeanRMSE": -1}
{"TrainCount": 9, "MeanTrainLoss": 0.03386625672814882, "MeanValidationLoss": 0.04322424506474482, "FinalMeanRMSE": -1}
{"TrainCount": 9, "MeanTrainLoss": 0.03382386235393894, "MeanValidationLoss": 0.04323055002054101, "FinalMeanRMSE": -1}
{"TrainCount": 9, "MeanTrainLoss": 0.03381883020408827, "MeanValidationLoss": 0.043236929384109224, "FinalMeanRMSE": 0.20793491472858108}
{"TrainCount": 10, "MeanTrainLoss": 0.03860044813043969, "MeanValidationLoss": 0.040897558410094396, "FinalMeanRMSE": -1}
{"TrainCount": 10, "MeanTrainLoss": 0.038487563936680715, "MeanValidationLoss": 0.04083143813613935, "FinalMeanRMSE": -1}
{"TrainCount": 10, "MeanTrainLoss": 0.038404962936696665, "MeanValidationLoss": 0.04079483909996582, "FinalMeanRMSE": -1}
{"TrainCount": 10, "MeanTrainLoss": 0.038349088447629125, "MeanValidationLoss": 0.04077635179831372, "FinalMeanRMSE": -1}
{"TrainCount": 10, "MeanTrainLoss": 0.03830982439059724, "MeanValidationLoss": 0.04076722883965977, "FinalMeanRMSE": -1}
{"TrainCount": 10, "MeanTrainLoss": 0.03828124797061807, "MeanValidationLoss": 0.04076291267491853, "FinalMeanRMSE": -1}
{"TrainCount": 10, "MeanTrainLoss": 0.03829195516294129, "MeanValidationLoss": 0.041117450807086856, "FinalMeanRMSE": -1}
{"TrainCount": 10, "MeanTrainLoss": 0.03829043429615277, "MeanValidationLoss": 0.04091878247396074, "FinalMeanRMSE": -1}
{"TrainCount": 10, "MeanTrainLoss": 0.03825423011471147, "MeanValidationLoss": 0.04085064566058248, "FinalMeanRMSE": -1}
{"TrainCount": 10, "MeanTrainLoss": 0.03823603929711446, "MeanValidationLoss": 0.04081460523711439, "FinalMeanRMSE": -1}
{"TrainCount": 10, "MeanTrainLoss": 0.03822410495761502, "MeanValidationLoss": 0.04079535450412618, "FinalMeanRMSE": -1}
{"TrainCount": 10, "MeanTrainLoss": 0.038215843164261874, "MeanValidationLoss": 0.040782348623553524, "FinalMeanRMSE": -1}
{"TrainCount": 10, "MeanTrainLoss": 0.0382094828241695, "MeanValidationLoss": 0.04077535173267994, "FinalMeanRMSE": -1}
{"TrainCount": 10, "MeanTrainLoss": 0.03820473645207903, "MeanValidationLoss": 0.04077127683172334, "FinalMeanRMSE": -1}
{"TrainCount": 10, "MeanTrainLoss": 0.03820105728002325, "MeanValidationLoss": 0.0407689906970197, "FinalMeanRMSE": 0.20191332433622733}
{"TrainCount": 11, "MeanTrainLoss": 0.03685591634580178, "MeanValidationLoss": 0.04499701504568452, "FinalMeanRMSE": -1}
{"TrainCount": 11, "MeanTrainLoss": 0.03683573262641291, "MeanValidationLoss": 0.0450555013076773, "FinalMeanRMSE": -1}
{"TrainCount": 11, "MeanTrainLoss": 0.03682610348317587, "MeanValidationLoss": 0.04509041181081321, "FinalMeanRMSE": -1}
{"TrainCount": 11, "MeanTrainLoss": 0.036822586599938555, "MeanValidationLoss": 0.04511366806273322, "FinalMeanRMSE": -1}
{"TrainCount": 11, "MeanTrainLoss": 0.03682119961723396, "MeanValidationLoss": 0.04512916804324462, "FinalMeanRMSE": -1}
{"TrainCount": 11, "MeanTrainLoss": 0.036820417483282915, "MeanValidationLoss": 0.04513960539040828, "FinalMeanRMSE": -1}
{"TrainCount": 11, "MeanTrainLoss": 0.036819775767833574, "MeanValidationLoss": 0.04514679715374913, "FinalMeanRMSE": -1}
{"TrainCount": 11, "MeanTrainLoss": 0.036819156388034055, "MeanValidationLoss": 0.04515190919240316, "FinalMeanRMSE": -1}
{"TrainCount": 11, "MeanTrainLoss": 0.03681853879444285, "MeanValidationLoss": 0.045155679137961376, "FinalMeanRMSE": -1}
{"TrainCount": 11, "MeanTrainLoss": 0.03681792948821451, "MeanValidationLoss": 0.04515856549047344, "FinalMeanRMSE": -1}
{"TrainCount": 11, "MeanTrainLoss": 0.03681733493831966, "MeanValidationLoss": 0.045160850588364894, "FinalMeanRMSE": -1}
{"TrainCount": 11, "MeanTrainLoss": 0.03681676266775275, "MeanValidationLoss": 0.04516270974934294, "FinalMeanRMSE": -1}
{"TrainCount": 11, "MeanTrainLoss": 0.03681621418111267, "MeanValidationLoss": 0.045164260868597955, "FinalMeanRMSE": -1}
{"TrainCount": 11, "MeanTrainLoss": 0.036815690451963416, "MeanValidationLoss": 0.0451655768243819, "FinalMeanRMSE": -1}
{"TrainCount": 11, "MeanTrainLoss": 0.03681519032972935, "MeanValidationLoss": 0.04516670570790189, "FinalMeanRMSE": 0.21252459627310916}
{"TrainCount": 12, "MeanTrainLoss": 0.04534822633536924, "MeanValidationLoss": 0.04313452664045882, "FinalMeanRMSE": -1}
{"TrainCount": 12, "MeanTrainLoss": 0.045049048928903934, "MeanValidationLoss": 0.04319729117753002, "FinalMeanRMSE": -1}
{"TrainCount": 12, "MeanTrainLoss": 0.04494461373371236, "MeanValidationLoss": 0.043222215038368754, "FinalMeanRMSE": -1}
{"TrainCount": 12, "MeanTrainLoss": 0.04489575940019944, "MeanValidationLoss": 0.04324077810116747, "FinalMeanRMSE": -1}
{"TrainCount": 12, "MeanTrainLoss": 0.044871299238014625, "MeanValidationLoss": 0.043255320952893805, "FinalMeanRMSE": -1}
{"TrainCount": 12, "MeanTrainLoss": 0.04485830076101447, "MeanValidationLoss": 0.04326581447282424, "FinalMeanRMSE": -1}
{"TrainCount": 12, "MeanTrainLoss": 0.04485089400736224, "MeanValidationLoss": 0.04327286490788595, "FinalMeanRMSE": -1}
{"TrainCount": 12, "MeanTrainLoss": 0.04484634066955382, "MeanValidationLoss": 0.04327737208608573, "FinalMeanRMSE": -1}
{"TrainCount": 12, "MeanTrainLoss": 0.044843321900908686, "MeanValidationLoss": 0.043280151834247244, "FinalMeanRMSE": -1}
{"TrainCount": 12, "MeanTrainLoss": 0.04484117788677456, "MeanValidationLoss": 0.04328183994308255, "FinalMeanRMSE": -1}
{"TrainCount": 12, "MeanTrainLoss": 0.0448395646169406, "MeanValidationLoss": 0.04328288424654338, "FinalMeanRMSE": -1}
{"TrainCount": 12, "MeanTrainLoss": 0.044838282584893606, "MeanValidationLoss": 0.04328358185122066, "FinalMeanRMSE": -1}
{"TrainCount": 12, "MeanTrainLoss": 0.04483722053280398, "MeanValidationLoss": 0.04328411723537024, "FinalMeanRMSE": -1}
{"TrainCount": 12, "MeanTrainLoss": 0.0448363058957733, "MeanValidationLoss": 0.04328459870269998, "FinalMeanRMSE": -1}
{"TrainCount": 12, "MeanTrainLoss": 0.04483549659993468, "MeanValidationLoss": 0.04328506902941394, "FinalMeanRMSE": 0.20805064048539118}
{"TrainCount": 13, "MeanTrainLoss": 0.04161153376723329, "MeanValidationLoss": 0.04754760282166699, "FinalMeanRMSE": -1}
{"TrainCount": 13, "MeanTrainLoss": 0.041180702904239294, "MeanValidationLoss": 0.04754237723201046, "FinalMeanRMSE": -1}
{"TrainCount": 13, "MeanTrainLoss": 0.041048910624037184, "MeanValidationLoss": 0.04757677924857244, "FinalMeanRMSE": -1}
{"TrainCount": 13, "MeanTrainLoss": 0.04098446620628238, "MeanValidationLoss": 0.0476140107107013, "FinalMeanRMSE": -1}
{"TrainCount": 13, "MeanTrainLoss": 0.04094899320043623, "MeanValidationLoss": 0.04764605930139278, "FinalMeanRMSE": -1}
{"TrainCount": 13, "MeanTrainLoss": 0.040927917572359244, "MeanValidationLoss": 0.04767170796013177, "FinalMeanRMSE": -1}
{"TrainCount": 13, "MeanTrainLoss": 0.040914425750573476, "MeanValidationLoss": 0.04769109563207178, "FinalMeanRMSE": -1}
{"TrainCount": 13, "MeanTrainLoss": 0.04090538377252718, "MeanValidationLoss": 0.04770622995673302, "FinalMeanRMSE": -1}
{"TrainCount": 13, "MeanTrainLoss": 0.04089882103726268, "MeanValidationLoss": 0.04771765580745326, "FinalMeanRMSE": -1}
{"TrainCount": 13, "MeanTrainLoss": 0.04089376721531153, "MeanValidationLoss": 0.04772599076496022, "FinalMeanRMSE": -1}
{"TrainCount": 13, "MeanTrainLoss": 0.040889869707946974, "MeanValidationLoss": 0.047732708923121606, "FinalMeanRMSE": -1}
{"TrainCount": 13, "MeanTrainLoss": 0.04088657470420003, "MeanValidationLoss": 0.047737806451544865, "FinalMeanRMSE": -1}
{"TrainCount": 13, "MeanTrainLoss": 0.04088371628895402, "MeanValidationLoss": 0.04774180281218317, "FinalMeanRMSE": -1}
{"TrainCount": 13, "MeanTrainLoss": 0.04088119848941763, "MeanValidationLoss": 0.04774510465725836, "FinalMeanRMSE": -1}
{"TrainCount": 13, "MeanTrainLoss": 0.04087886864629885, "MeanValidationLoss": 0.04774761961358468, "FinalMeanRMSE": 0.2185122849805348}
{"TrainCount": 14, "MeanTrainLoss": 0.04928720869169458, "MeanValidationLoss": 0.0564946581464295, "FinalMeanRMSE": -1}
{"TrainCount": 14, "MeanTrainLoss": 0.04918640062199667, "MeanValidationLoss": 0.0563354499022895, "FinalMeanRMSE": -1}
{"TrainCount": 14, "MeanTrainLoss": 0.049136099772615065, "MeanValidationLoss": 0.0562271447538965, "FinalMeanRMSE": -1}
{"TrainCount": 14, "MeanTrainLoss": 0.04910171430893698, "MeanValidationLoss": 0.056151171616458016, "FinalMeanRMSE": -1}
{"TrainCount": 14, "MeanTrainLoss": 0.049079526737408216, "MeanValidationLoss": 0.05609681391205627, "FinalMeanRMSE": -1}
{"TrainCount": 14, "MeanTrainLoss": 0.04906461520979746, "MeanValidationLoss": 0.05605682657763863, "FinalMeanRMSE": -1}
{"TrainCount": 14, "MeanTrainLoss": 0.049053770558275055, "MeanValidationLoss": 0.05602651857272565, "FinalMeanRMSE": -1}
{"TrainCount": 14, "MeanTrainLoss": 0.049045208577434635, "MeanValidationLoss": 0.05600286373122387, "FinalMeanRMSE": -1}
{"TrainCount": 14, "MeanTrainLoss": 0.049038008060268375, "MeanValidationLoss": 0.05598390599091848, "FinalMeanRMSE": -1}
{"TrainCount": 14, "MeanTrainLoss": 0.04903170920845857, "MeanValidationLoss": 0.05596835341657703, "FinalMeanRMSE": -1}
{"TrainCount": 14, "MeanTrainLoss": 0.0490261057563422, "MeanValidationLoss": 0.055955350900279636, "FinalMeanRMSE": -1}
{"TrainCount": 14, "MeanTrainLoss": 0.049020977912265846, "MeanValidationLoss": 0.0559442628414259, "FinalMeanRMSE": -1}
{"TrainCount": 14, "MeanTrainLoss": 0.04901618930575667, "MeanValidationLoss": 0.05593464484819943, "FinalMeanRMSE": -1}
{"TrainCount": 14, "MeanTrainLoss": 0.04901170391350408, "MeanValidationLoss": 0.05592618385950724, "FinalMeanRMSE": -1}
{"TrainCount": 14, "MeanTrainLoss": 0.0490075088648577, "MeanValidationLoss": 0.05591866036802986, "FinalMeanRMSE": 0.23647126774244015}
{"TrainCount": 15, "MeanTrainLoss": 0.050408111233264205, "MeanValidationLoss": 0.048249178240075706, "FinalMeanRMSE": -1}
{"TrainCount": 15, "MeanTrainLoss": 0.05017754547297955, "MeanValidationLoss": 0.04828569832025096, "FinalMeanRMSE": -1}
{"TrainCount": 15, "MeanTrainLoss": 0.05013710418716073, "MeanValidationLoss": 0.04830045022536069, "FinalMeanRMSE": -1}
{"TrainCount": 15, "MeanTrainLoss": 0.050120462321986754, "MeanValidationLoss": 0.04830909857992083, "FinalMeanRMSE": -1}
{"TrainCount": 15, "MeanTrainLoss": 0.05011053401976824, "MeanValidationLoss": 0.04831525639165193, "FinalMeanRMSE": -1}
{"TrainCount": 15, "MeanTrainLoss": 0.05010343625520666, "MeanValidationLoss": 0.04831964141922072, "FinalMeanRMSE": -1}
{"TrainCount": 15, "MeanTrainLoss": 0.050097793837388355, "MeanValidationLoss": 0.0483225752832368, "FinalMeanRMSE": -1}
{"TrainCount": 15, "MeanTrainLoss": 0.05009296229109168, "MeanValidationLoss": 0.048324330756440756, "FinalMeanRMSE": -1}
{"TrainCount": 15, "MeanTrainLoss": 0.050088602832208076, "MeanValidationLoss": 0.048325158073566854, "FinalMeanRMSE": -1}
{"TrainCount": 15, "MeanTrainLoss": 0.0500845226769646, "MeanValidationLoss": 0.04832527138059959, "FinalMeanRMSE": -1}
{"TrainCount": 15, "MeanTrainLoss": 0.05008058762177825, "MeanValidationLoss": 0.048324860795401034, "FinalMeanRMSE": -1}
{"TrainCount": 15, "MeanTrainLoss": 0.05007672188803554, "MeanValidationLoss": 0.048324070044327525, "FinalMeanRMSE": -1}
{"TrainCount": 15, "MeanTrainLoss": 0.0500741599748532, "MeanValidationLoss": 0.04832438542507589, "FinalMeanRMSE": -1}
{"TrainCount": 15, "MeanTrainLoss": 0.05006769597530365, "MeanValidationLoss": 0.04832312650978565, "FinalMeanRMSE": -1}
{"TrainCount": 15, "MeanTrainLoss": 0.05006381316731374, "MeanValidationLoss": 0.048321633227169515, "FinalMeanRMSE": 0.21982182110170834}
{"TrainCount": 16, "MeanTrainLoss": 0.04263994810406608, "MeanValidationLoss": 0.055562232221875875, "FinalMeanRMSE": -1}
{"TrainCount": 16, "MeanTrainLoss": 0.042047530465354824, "MeanValidationLoss": 0.056029249175160126, "FinalMeanRMSE": -1}
{"TrainCount": 16, "MeanTrainLoss": 0.041822053454440046, "MeanValidationLoss": 0.05634030690671463, "FinalMeanRMSE": -1}
{"TrainCount": 16, "MeanTrainLoss": 0.04170554287806906, "MeanValidationLoss": 0.05658077613923325, "FinalMeanRMSE": -1}
{"TrainCount": 16, "MeanTrainLoss": 0.04164258141559784, "MeanValidationLoss": 0.056747462815607934, "FinalMeanRMSE": -1}
{"TrainCount": 16, "MeanTrainLoss": 0.04160691451544714, "MeanValidationLoss": 0.0568702678368809, "FinalMeanRMSE": -1}
{"TrainCount": 16, "MeanTrainLoss": 0.04158435391280988, "MeanValidationLoss": 0.05694322763605321, "FinalMeanRMSE": -1}
{"TrainCount": 16, "MeanTrainLoss": 0.04157058776102283, "MeanValidationLoss": 0.05699910209896354, "FinalMeanRMSE": -1}
{"TrainCount": 16, "MeanTrainLoss": 0.041562577931567875, "MeanValidationLoss": 0.05700820154513269, "FinalMeanRMSE": -1}
{"TrainCount": 16, "MeanTrainLoss": 0.041556252117710885, "MeanValidationLoss": 0.05705326904279483, "FinalMeanRMSE": -1}
{"TrainCount": 16, "MeanTrainLoss": 0.04155072776807679, "MeanValidationLoss": 0.05707221326494652, "FinalMeanRMSE": -1}
{"TrainCount": 16, "MeanTrainLoss": 0.04150515016958569, "MeanValidationLoss": 0.05678733798327055, "FinalMeanRMSE": -1}
{"TrainCount": 16, "MeanTrainLoss": 0.041569269448518756, "MeanValidationLoss": 0.05678352743024884, "FinalMeanRMSE": -1}
{"TrainCount": 16, "MeanTrainLoss": 0.041595290413107534, "MeanValidationLoss": 0.056842064377384705, "FinalMeanRMSE": -1}
{"TrainCount": 16, "MeanTrainLoss": 0.041556151226313426, "MeanValidationLoss": 0.05696444469291751, "FinalMeanRMSE": 0.23867224930028777}
{"TrainCount": 17, "MeanTrainLoss": 0.04417923420344765, "MeanValidationLoss": 0.050367352863152824, "FinalMeanRMSE": -1}
{"TrainCount": 17, "MeanTrainLoss": 0.04375959573339723, "MeanValidationLoss": 0.05024740502641008, "FinalMeanRMSE": -1}
{"TrainCount": 17, "MeanTrainLoss": 0.04369434413620511, "MeanValidationLoss": 0.05020585872076295, "FinalMeanRMSE": -1}
{"TrainCount": 17, "MeanTrainLoss": 0.043654807283121246, "MeanValidationLoss": 0.05018432096049592, "FinalMeanRMSE": -1}
{"TrainCount": 17, "MeanTrainLoss": 0.043630005080693354, "MeanValidationLoss": 0.05017269133134289, "FinalMeanRMSE": -1}
{"TrainCount": 17, "MeanTrainLoss": 0.04361428042340889, "MeanValidationLoss": 0.05016695084917295, "FinalMeanRMSE": -1}
{"TrainCount": 17, "MeanTrainLoss": 0.043604272664319314, "MeanValidationLoss": 0.05016479361522663, "FinalMeanRMSE": -1}
{"TrainCount": 17, "MeanTrainLoss": 0.04359790080979108, "MeanValidationLoss": 0.05016478452014851, "FinalMeanRMSE": -1}
{"TrainCount": 17, "MeanTrainLoss": 0.043593861339968405, "MeanValidationLoss": 0.05016599977025399, "FinalMeanRMSE": -1}
{"TrainCount": 17, "MeanTrainLoss": 0.04359133452954394, "MeanValidationLoss": 0.05016786301950435, "FinalMeanRMSE": -1}
{"TrainCount": 17, "MeanTrainLoss": 0.043589771699341376, "MeanValidationLoss": 0.050170038712096285, "FinalMeanRMSE": -1}
{"TrainCount": 17, "MeanTrainLoss": 0.04358881833437711, "MeanValidationLoss": 0.05017231935047888, "FinalMeanRMSE": -1}
{"TrainCount": 17, "MeanTrainLoss": 0.04358825211591444, "MeanValidationLoss": 0.050174549333863075, "FinalMeanRMSE": -1}
{"TrainCount": 17, "MeanTrainLoss": 0.043587920188769426, "MeanValidationLoss": 0.05017663652563954, "FinalMeanRMSE": -1}
{"TrainCount": 17, "MeanTrainLoss": 0.043587722214366235, "MeanValidationLoss": 0.05017855089974475, "FinalMeanRMSE": 0.22400569777574095}
{"TrainCount": 18, "MeanTrainLoss": 0.043275967073755535, "MeanValidationLoss": 0.056476294449189814, "FinalMeanRMSE": -1}
{"TrainCount": 18, "MeanTrainLoss": 0.04325946593823714, "MeanValidationLoss": 0.056592359866310914, "FinalMeanRMSE": -1}
{"TrainCount": 18, "MeanTrainLoss": 0.043253678518037, "MeanValidationLoss": 0.056660938008529387, "FinalMeanRMSE": -1}
{"TrainCount": 18, "MeanTrainLoss": 0.04324601819299585, "MeanValidationLoss": 0.05670764251816564, "FinalMeanRMSE": -1}
{"TrainCount": 18, "MeanTrainLoss": 0.04323956230276726, "MeanValidationLoss": 0.05674016802776151, "FinalMeanRMSE": -1}
{"TrainCount": 18, "MeanTrainLoss": 0.04323412454497766, "MeanValidationLoss": 0.05676274683053901, "FinalMeanRMSE": -1}
{"TrainCount": 18, "MeanTrainLoss": 0.04322934396019796, "MeanValidationLoss": 0.05677833517150181, "FinalMeanRMSE": -1}
{"TrainCount": 18, "MeanTrainLoss": 0.04322500539019825, "MeanValidationLoss": 0.056789038839136684, "FinalMeanRMSE": -1}
{"TrainCount": 18, "MeanTrainLoss": 0.04322099380528297, "MeanValidationLoss": 0.05679634267964014, "FinalMeanRMSE": -1}
{"TrainCount": 18, "MeanTrainLoss": 0.04321724055259208, "MeanValidationLoss": 0.05680130930935464, "FinalMeanRMSE": -1}
{"TrainCount": 18, "MeanTrainLoss": 0.043213709689131595, "MeanValidationLoss": 0.05680466552333134, "FinalMeanRMSE": -1}
{"TrainCount": 18, "MeanTrainLoss": 0.04321035978997626, "MeanValidationLoss": 0.056806912600267226, "FinalMeanRMSE": -1}
{"TrainCount": 18, "MeanTrainLoss": 0.04320716573970347, "MeanValidationLoss": 0.05680838745178246, "FinalMeanRMSE": -1}
{"TrainCount": 18, "MeanTrainLoss": 0.04320411100923046, "MeanValidationLoss": 0.05680933167658201, "FinalMeanRMSE": -1}
{"TrainCount": 18, "MeanTrainLoss": 0.043201173648117035, "MeanValidationLoss": 0.05680990509870576, "FinalMeanRMSE": 0.23834828550995493}
{"TrainCount": 19, "MeanTrainLoss": 0.05008320653378361, "MeanValidationLoss": 0.04753037496949687, "FinalMeanRMSE": -1}
{"TrainCount": 19, "MeanTrainLoss": 0.04975386429766212, "MeanValidationLoss": 0.04761786176399751, "FinalMeanRMSE": -1}
{"TrainCount": 19, "MeanTrainLoss": 0.04960902434105825, "MeanValidationLoss": 0.047716018693013625, "FinalMeanRMSE": -1}
{"TrainCount": 19, "MeanTrainLoss": 0.04966427616850294, "MeanValidationLoss": 0.047789012934222365, "FinalMeanRMSE": -1}
{"TrainCount": 19, "MeanTrainLoss": 0.04949624437575388, "MeanValidationLoss": 0.047855602204799653, "FinalMeanRMSE": -1}
{"TrainCount": 19, "MeanTrainLoss": 0.049472464696325436, "MeanValidationLoss": 0.04790765945658539, "FinalMeanRMSE": -1}
{"TrainCount": 19, "MeanTrainLoss": 0.04945606876051787, "MeanValidationLoss": 0.047946927719043964, "FinalMeanRMSE": -1}
{"TrainCount": 19, "MeanTrainLoss": 0.04944459312040397, "MeanValidationLoss": 0.04797632039496393, "FinalMeanRMSE": -1}
{"TrainCount": 19, "MeanTrainLoss": 0.04943600276654417, "MeanValidationLoss": 0.04799832805539622, "FinalMeanRMSE": -1}
{"TrainCount": 19, "MeanTrainLoss": 0.04942917674779892, "MeanValidationLoss": 0.04801490568753445, "FinalMeanRMSE": -1}
{"TrainCount": 19, "MeanTrainLoss": 0.04942350530564183, "MeanValidationLoss": 0.04802755605090748, "FinalMeanRMSE": -1}
{"TrainCount": 19, "MeanTrainLoss": 0.049418679685002624, "MeanValidationLoss": 0.048037358982996506, "FinalMeanRMSE": -1}
{"TrainCount": 19, "MeanTrainLoss": 0.04941799725697498, "MeanValidationLoss": 0.04804174556876674, "FinalMeanRMSE": -1}
{"TrainCount": 19, "MeanTrainLoss": 0.049411761459678114, "MeanValidationLoss": 0.04804775394273527, "FinalMeanRMSE": -1}
{"TrainCount": 19, "MeanTrainLoss": 0.049408224872266406, "MeanValidationLoss": 0.048052391455028994, "FinalMeanRMSE": 0.21920855575613177}
{"TrainCount": 20, "MeanTrainLoss": 0.056091304517844144, "MeanValidationLoss": 0.04761012396321888, "FinalMeanRMSE": -1}
{"TrainCount": 20, "MeanTrainLoss": 0.05587894123266725, "MeanValidationLoss": 0.047567031541317265, "FinalMeanRMSE": -1}
{"TrainCount": 20, "MeanTrainLoss": 0.055792842279462254, "MeanValidationLoss": 0.047563065195066034, "FinalMeanRMSE": -1}
{"TrainCount": 20, "MeanTrainLoss": 0.05575014250535591, "MeanValidationLoss": 0.04757908645984346, "FinalMeanRMSE": -1}
{"TrainCount": 20, "MeanTrainLoss": 0.0557290226732399, "MeanValidationLoss": 0.04760235861207532, "FinalMeanRMSE": -1}
{"TrainCount": 20, "MeanTrainLoss": 0.05571858927461446, "MeanValidationLoss": 0.0476260664694253, "FinalMeanRMSE": -1}
{"TrainCount": 20, "MeanTrainLoss": 0.05571307325187851, "MeanValidationLoss": 0.04764729571201808, "FinalMeanRMSE": -1}
{"TrainCount": 20, "MeanTrainLoss": 0.05570958401350414, "MeanValidationLoss": 0.04766525478709412, "FinalMeanRMSE": -1}
{"TrainCount": 20, "MeanTrainLoss": 0.05570677219360482, "MeanValidationLoss": 0.04768011755252306, "FinalMeanRMSE": -1}
{"TrainCount": 20, "MeanTrainLoss": 0.05570406111724237, "MeanValidationLoss": 0.0476923891422847, "FinalMeanRMSE": -1}
{"TrainCount": 20, "MeanTrainLoss": 0.05570124658007248, "MeanValidationLoss": 0.047702634053244354, "FinalMeanRMSE": -1}
{"TrainCount": 20, "MeanTrainLoss": 0.05569828038706499, "MeanValidationLoss": 0.047711339276448814, "FinalMeanRMSE": -1}
{"TrainCount": 20, "MeanTrainLoss": 0.05569517485359136, "MeanValidationLoss": 0.04771889350583068, "FinalMeanRMSE": -1}
{"TrainCount": 20, "MeanTrainLoss": 0.05569196127209009, "MeanValidationLoss": 0.04772560577564886, "FinalMeanRMSE": -1}
{"TrainCount": 20, "MeanTrainLoss": 0.055688659766433286, "MeanValidationLoss": 0.047731698141776704, "FinalMeanRMSE": 0.21847585270135106}
{"TrainCount": 21, "MeanTrainLoss": 0.058445647111027677, "MeanValidationLoss": 0.05652992038433153, "FinalMeanRMSE": -1}
{"TrainCount": 21, "MeanTrainLoss": 0.05827003294591101, "MeanValidationLoss": 0.05654250485194394, "FinalMeanRMSE": -1}
{"TrainCount": 21, "MeanTrainLoss": 0.058240017312380196, "MeanValidationLoss": 0.0565681027090095, "FinalMeanRMSE": -1}
{"TrainCount": 21, "MeanTrainLoss": 0.058219521537918865, "MeanValidationLoss": 0.05658380962536831, "FinalMeanRMSE": -1}
{"TrainCount": 21, "MeanTrainLoss": 0.05820398198881728, "MeanValidationLoss": 0.056593226722258624, "FinalMeanRMSE": -1}
{"TrainCount": 21, "MeanTrainLoss": 0.05819181437420052, "MeanValidationLoss": 0.056599202415635506, "FinalMeanRMSE": -1}
{"TrainCount": 21, "MeanTrainLoss": 0.05818211976912623, "MeanValidationLoss": 0.05660315941680561, "FinalMeanRMSE": -1}
{"TrainCount": 21, "MeanTrainLoss": 0.05817422644032891, "MeanValidationLoss": 0.05660577232012651, "FinalMeanRMSE": -1}
{"TrainCount": 21, "MeanTrainLoss": 0.05816767025017225, "MeanValidationLoss": 0.05660738806920317, "FinalMeanRMSE": -1}
{"TrainCount": 21, "MeanTrainLoss": 0.058162117176443165, "MeanValidationLoss": 0.05660822581161152, "FinalMeanRMSE": -1}
{"TrainCount": 21, "MeanTrainLoss": 0.058157332955974424, "MeanValidationLoss": 0.056608429839534145, "FinalMeanRMSE": -1}
{"TrainCount": 21, "MeanTrainLoss": 0.058153157044063576, "MeanValidationLoss": 0.0566080858237233, "FinalMeanRMSE": -1}
{"TrainCount": 21, "MeanTrainLoss": 0.058149481254197846, "MeanValidationLoss": 0.05660725365286349, "FinalMeanRMSE": -1}
{"TrainCount": 21, "MeanTrainLoss": 0.05814618279031111, "MeanValidationLoss": 0.05660601679093677, "FinalMeanRMSE": -1}
{"TrainCount": 21, "MeanTrainLoss": 0.058143166194573305, "MeanValidationLoss": 0.05660447414931664, "FinalMeanRMSE": 0.23791694747092829}
{"TrainCount": 22, "MeanTrainLoss": 0.047937238452770904, "MeanValidationLoss": 0.05152395075699042, "FinalMeanRMSE": -1}
{"TrainCount": 22, "MeanTrainLoss": 0.04763729061085375, "MeanValidationLoss": 0.051619323722103184, "FinalMeanRMSE": -1}
{"TrainCount": 22, "MeanTrainLoss": 0.04754557409895617, "MeanValidationLoss": 0.051753081076326424, "FinalMeanRMSE": -1}
{"TrainCount": 22, "MeanTrainLoss": 0.0475063812583104, "MeanValidationLoss": 0.051871031653462796, "FinalMeanRMSE": -1}
{"TrainCount": 22, "MeanTrainLoss": 0.04749352171368984, "MeanValidationLoss": 0.05196201204382188, "FinalMeanRMSE": -1}
{"TrainCount": 22, "MeanTrainLoss": 0.04749196699546327, "MeanValidationLoss": 0.05202734012875641, "FinalMeanRMSE": -1}
{"TrainCount": 22, "MeanTrainLoss": 0.04749436816291386, "MeanValidationLoss": 0.05207218491194541, "FinalMeanRMSE": -1}
{"TrainCount": 22, "MeanTrainLoss": 0.04749764501276929, "MeanValidationLoss": 0.052102130843184845, "FinalMeanRMSE": -1}
{"TrainCount": 22, "MeanTrainLoss": 0.04750071323819851, "MeanValidationLoss": 0.052121800506672665, "FinalMeanRMSE": -1}
{"TrainCount": 22, "MeanTrainLoss": 0.047503223327727405, "MeanValidationLoss": 0.05213452261268047, "FinalMeanRMSE": -1}
{"TrainCount": 22, "MeanTrainLoss": 0.04750515653553907, "MeanValidationLoss": 0.052142641436286837, "FinalMeanRMSE": -1}
{"TrainCount": 22, "MeanTrainLoss": 0.04750661083159435, "MeanValidationLoss": 0.05214775031247334, "FinalMeanRMSE": -1}
{"TrainCount": 22, "MeanTrainLoss": 0.047507690050190794, "MeanValidationLoss": 0.05215091040434196, "FinalMeanRMSE": -1}
{"TrainCount": 22, "MeanTrainLoss": 0.047508481072559665, "MeanValidationLoss": 0.05215281648942602, "FinalMeanRMSE": -1}
{"TrainCount": 22, "MeanTrainLoss": 0.0475090539711936, "MeanValidationLoss": 0.052153924229549384, "FinalMeanRMSE": 0.22837233786982397}
{"TrainCount": 23, "MeanTrainLoss": 0.0568055396918023, "MeanValidationLoss": 0.05814722872206143, "FinalMeanRMSE": -1}
{"TrainCount": 23, "MeanTrainLoss": 0.056284024913122156, "MeanValidationLoss": 0.05819761682124365, "FinalMeanRMSE": -1}
{"TrainCount": 23, "MeanTrainLoss": 0.05615821907130798, "MeanValidationLoss": 0.05830879128050236, "FinalMeanRMSE": -1}
{"TrainCount": 23, "MeanTrainLoss": 0.0561108736856149, "MeanValidationLoss": 0.0584051108786038, "FinalMeanRMSE": -1}
{"TrainCount": 23, "MeanTrainLoss": 0.05609003742142479, "MeanValidationLoss": 0.05847886905428909, "FinalMeanRMSE": -1}
{"TrainCount": 23, "MeanTrainLoss": 0.05607888421209732, "MeanValidationLoss": 0.05853418225333804, "FinalMeanRMSE": -1}
{"TrainCount": 23, "MeanTrainLoss": 0.05607137901358085, "MeanValidationLoss": 0.05857625905246962, "FinalMeanRMSE": -1}
{"TrainCount": 23, "MeanTrainLoss": 0.056065295562885774, "MeanValidationLoss": 0.05860924543369384, "FinalMeanRMSE": -1}
{"TrainCount": 23, "MeanTrainLoss": 0.05605994707877093, "MeanValidationLoss": 0.0586361823869603, "FinalMeanRMSE": -1}
{"TrainCount": 23, "MeanTrainLoss": 0.056054966122207076, "MeanValidationLoss": 0.05865903713163875, "FinalMeanRMSE": -1}
{"TrainCount": 23, "MeanTrainLoss": 0.056050368140239525, "MeanValidationLoss": 0.05867915245748702, "FinalMeanRMSE": -1}
{"TrainCount": 23, "MeanTrainLoss": 0.056046048160826804, "MeanValidationLoss": 0.05869730065266291, "FinalMeanRMSE": -1}
{"TrainCount": 23, "MeanTrainLoss": 0.056042050002235, "MeanValidationLoss": 0.058714128321125394, "FinalMeanRMSE": -1}
{"TrainCount": 23, "MeanTrainLoss": 0.056038311994311835, "MeanValidationLoss": 0.0587299931794405, "FinalMeanRMSE": -1}
{"TrainCount": 23, "MeanTrainLoss": 0.05603482649467959, "MeanValidationLoss": 0.058745130186989195, "FinalMeanRMSE": 0.2423739462424771}
{"TrainCount": 24, "MeanTrainLoss": 0.046967212593801363, "MeanValidationLoss": 0.05284466185664709, "FinalMeanRMSE": -1}
{"TrainCount": 24, "MeanTrainLoss": 0.046684830312293264, "MeanValidationLoss": 0.05312772833668025, "FinalMeanRMSE": -1}
{"TrainCount": 24, "MeanTrainLoss": 0.04663687001745453, "MeanValidationLoss": 0.053178721077322605, "FinalMeanRMSE": -1}
{"TrainCount": 24, "MeanTrainLoss": 0.04660416130627888, "MeanValidationLoss": 0.05318115526332264, "FinalMeanRMSE": -1}
{"TrainCount": 24, "MeanTrainLoss": 0.046577990827222, "MeanValidationLoss": 0.053175777834249455, "FinalMeanRMSE": -1}
{"TrainCount": 24, "MeanTrainLoss": 0.04655667578834447, "MeanValidationLoss": 0.0531708953742784, "FinalMeanRMSE": -1}
{"TrainCount": 24, "MeanTrainLoss": 0.04653911015168857, "MeanValidationLoss": 0.053168119450586034, "FinalMeanRMSE": -1}
{"TrainCount": 24, "MeanTrainLoss": 0.04655458263262433, "MeanValidationLoss": 0.05318304269978431, "FinalMeanRMSE": -1}
{"TrainCount": 24, "MeanTrainLoss": 0.04651310619091238, "MeanValidationLoss": 0.053175393063410195, "FinalMeanRMSE": -1}
{"TrainCount": 24, "MeanTrainLoss": 0.0465029195895188, "MeanValidationLoss": 0.05317521583190007, "FinalMeanRMSE": -1}
{"TrainCount": 24, "MeanTrainLoss": 0.04649448480405836, "MeanValidationLoss": 0.05317900349608565, "FinalMeanRMSE": -1}
{"TrainCount": 24, "MeanTrainLoss": 0.046487481862101665, "MeanValidationLoss": 0.05318457490399172, "FinalMeanRMSE": -1}
{"TrainCount": 24, "MeanTrainLoss": 0.04648168121916489, "MeanValidationLoss": 0.05319126011875175, "FinalMeanRMSE": -1}
{"TrainCount": 24, "MeanTrainLoss": 0.04647688603866663, "MeanValidationLoss": 0.05319870298503071, "FinalMeanRMSE": -1}
{"TrainCount": 24, "MeanTrainLoss": 0.04647292881428258, "MeanValidationLoss": 0.05320662185329955, "FinalMeanRMSE": 0.23066560717596654}
{"TrainCount": 25, "MeanTrainLoss": 0.05803048985772857, "MeanValidationLoss": 0.055501730019188206, "FinalMeanRMSE": -1}
{"TrainCount": 25, "MeanTrainLoss": 0.057656267599440085, "MeanValidationLoss": 0.05518142221863642, "FinalMeanRMSE": -1}
{"TrainCount": 25, "MeanTrainLoss": 0.05754142299148382, "MeanValidationLoss": 0.05501463022467661, "FinalMeanRMSE": -1}
{"TrainCount": 25, "MeanTrainLoss": 0.057457559011584405, "MeanValidationLoss": 0.054897461998603334, "FinalMeanRMSE": -1}
{"TrainCount": 25, "MeanTrainLoss": 0.05739323176516622, "MeanValidationLoss": 0.05481119944018952, "FinalMeanRMSE": -1}
{"TrainCount": 25, "MeanTrainLoss": 0.05734276029043922, "MeanValidationLoss": 0.05474822493517293, "FinalMeanRMSE": -1}
{"TrainCount": 25, "MeanTrainLoss": 0.05730289533442142, "MeanValidationLoss": 0.054703422813816405, "FinalMeanRMSE": -1}
{"TrainCount": 25, "MeanTrainLoss": 0.057271475480029393, "MeanValidationLoss": 0.054672893543334836, "FinalMeanRMSE": -1}
{"TrainCount": 25, "MeanTrainLoss": 0.057243790850043295, "MeanValidationLoss": 0.054653196581872864, "FinalMeanRMSE": -1}
{"TrainCount": 25, "MeanTrainLoss": 0.05723207439204642, "MeanValidationLoss": 0.054818048765525706, "FinalMeanRMSE": -1}
{"TrainCount": 25, "MeanTrainLoss": 0.057178477322061855, "MeanValidationLoss": 0.05473060866372775, "FinalMeanRMSE": -1}
{"TrainCount": 25, "MeanTrainLoss": 0.057173145861894474, "MeanValidationLoss": 0.05468635089629519, "FinalMeanRMSE": -1}
{"TrainCount": 25, "MeanTrainLoss": 0.057169235413711446, "MeanValidationLoss": 0.054664826894228434, "FinalMeanRMSE": -1}
{"TrainCount": 25, "MeanTrainLoss": 0.057206903781522725, "MeanValidationLoss": 0.05505686365397631, "FinalMeanRMSE": -1}
{"TrainCount": 25, "MeanTrainLoss": 0.057120629688542264, "MeanValidationLoss": 0.054890039989554426, "FinalMeanRMSE": 0.23428623546866534}
{"TrainCount": 26, "MeanTrainLoss": 0.05541317387400666, "MeanValidationLoss": 0.06251556287267118, "FinalMeanRMSE": -1}
{"TrainCount": 26, "MeanTrainLoss": 0.05543849093962736, "MeanValidationLoss": 0.06267422135734697, "FinalMeanRMSE": -1}
{"TrainCount": 26, "MeanTrainLoss": 0.0553154074297022, "MeanValidationLoss": 0.06300586236114057, "FinalMeanRMSE": -1}
{"TrainCount": 26, "MeanTrainLoss": 0.055495048362167426, "MeanValidationLoss": 0.06276863365930997, "FinalMeanRMSE": -1}
{"TrainCount": 26, "MeanTrainLoss": 0.0553850976003747, "MeanValidationLoss": 0.06281784270230258, "FinalMeanRMSE": -1}
{"TrainCount": 26, "MeanTrainLoss": 0.0552894551368568, "MeanValidationLoss": 0.06286974353362798, "FinalMeanRMSE": -1}
{"TrainCount": 26, "MeanTrainLoss": 0.055276586319019126, "MeanValidationLoss": 0.06290483177142657, "FinalMeanRMSE": -1}
{"TrainCount": 26, "MeanTrainLoss": 0.055263897266369384, "MeanValidationLoss": 0.06293170471233112, "FinalMeanRMSE": -1}
{"TrainCount": 26, "MeanTrainLoss": 0.05525278740341445, "MeanValidationLoss": 0.06295170278747297, "FinalMeanRMSE": -1}
{"TrainCount": 26, "MeanTrainLoss": 0.05524307042940117, "MeanValidationLoss": 0.06296620963266222, "FinalMeanRMSE": -1}
{"TrainCount": 26, "MeanTrainLoss": 0.0552348745008387, "MeanValidationLoss": 0.0629781771766201, "FinalMeanRMSE": -1}
{"TrainCount": 26, "MeanTrainLoss": 0.0552271675021326, "MeanValidationLoss": 0.06298643789381744, "FinalMeanRMSE": -1}
{"TrainCount": 26, "MeanTrainLoss": 0.05522007854285755, "MeanValidationLoss": 0.06299236069267762, "FinalMeanRMSE": -1}
{"TrainCount": 26, "MeanTrainLoss": 0.05521348186185156, "MeanValidationLoss": 0.06299652750047233, "FinalMeanRMSE": -1}
{"TrainCount": 26, "MeanTrainLoss": 0.0552072467025123, "MeanValidationLoss": 0.06299928358536072, "FinalMeanRMSE": 0.2509965788070323}
{"TrainCount": 27, "MeanTrainLoss": 0.05365284063197948, "MeanValidationLoss": 0.05700626777064416, "FinalMeanRMSE": -1}
{"TrainCount": 27, "MeanTrainLoss": 0.05261079386079985, "MeanValidationLoss": 0.057100870501785334, "FinalMeanRMSE": -1}
{"TrainCount": 27, "MeanTrainLoss": 0.05241848801427882, "MeanValidationLoss": 0.05687223001222107, "FinalMeanRMSE": -1}
{"TrainCount": 27, "MeanTrainLoss": 0.05236036950617041, "MeanValidationLoss": 0.056617974164374064, "FinalMeanRMSE": -1}
{"TrainCount": 27, "MeanTrainLoss": 0.052361095422192624, "MeanValidationLoss": 0.05653118206696077, "FinalMeanRMSE": -1}
{"TrainCount": 27, "MeanTrainLoss": 0.052387668752995616, "MeanValidationLoss": 0.056488797680373765, "FinalMeanRMSE": -1}
{"TrainCount": 27, "MeanTrainLoss": 0.05241820849405627, "MeanValidationLoss": 0.05646369695838246, "FinalMeanRMSE": -1}
{"TrainCount": 27, "MeanTrainLoss": 0.052447815648993555, "MeanValidationLoss": 0.05644743948563103, "FinalMeanRMSE": -1}
{"TrainCount": 27, "MeanTrainLoss": 0.05247462420319488, "MeanValidationLoss": 0.05643635505367933, "FinalMeanRMSE": -1}
{"TrainCount": 27, "MeanTrainLoss": 0.05249784088041815, "MeanValidationLoss": 0.05642846766367686, "FinalMeanRMSE": -1}
{"TrainCount": 27, "MeanTrainLoss": 0.05251730446927032, "MeanValidationLoss": 0.05642258506978362, "FinalMeanRMSE": -1}
{"TrainCount": 27, "MeanTrainLoss": 0.05253321978083828, "MeanValidationLoss": 0.05641800388038333, "FinalMeanRMSE": -1}
{"TrainCount": 27, "MeanTrainLoss": 0.052545968145422534, "MeanValidationLoss": 0.05641422833690196, "FinalMeanRMSE": -1}
{"TrainCount": 27, "MeanTrainLoss": 0.052555952184846294, "MeanValidationLoss": 0.05641093286426186, "FinalMeanRMSE": -1}
{"TrainCount": 27, "MeanTrainLoss": 0.05256357629280574, "MeanValidationLoss": 0.05640795815987321, "FinalMeanRMSE": 0.23750359296225854}
{"TrainCount": 28, "MeanTrainLoss": 0.056932969549834206, "MeanValidationLoss": 0.05684642315085171, "FinalMeanRMSE": -1}
{"TrainCount": 28, "MeanTrainLoss": 0.05625731182751222, "MeanValidationLoss": 0.057280031604725015, "FinalMeanRMSE": -1}
{"TrainCount": 28, "MeanTrainLoss": 0.056045408275334226, "MeanValidationLoss": 0.05751515933644702, "FinalMeanRMSE": -1}
{"TrainCount": 28, "MeanTrainLoss": 0.05594647071119144, "MeanValidationLoss": 0.057691316332733424, "FinalMeanRMSE": -1}
{"TrainCount": 28, "MeanTrainLoss": 0.05589078739013153, "MeanValidationLoss": 0.05782669163935366, "FinalMeanRMSE": -1}
{"TrainCount": 28, "MeanTrainLoss": 0.055858587937839835, "MeanValidationLoss": 0.05792969081834046, "FinalMeanRMSE": -1}
{"TrainCount": 28, "MeanTrainLoss": 0.05583920048506201, "MeanValidationLoss": 0.058007162478235036, "FinalMeanRMSE": -1}
{"TrainCount": 28, "MeanTrainLoss": 0.055826980092328546, "MeanValidationLoss": 0.05806494552141044, "FinalMeanRMSE": -1}
{"TrainCount": 28, "MeanTrainLoss": 0.05581888541866087, "MeanValidationLoss": 0.05810780840659002, "FinalMeanRMSE": -1}
{"TrainCount": 28, "MeanTrainLoss": 0.0558132468196282, "MeanValidationLoss": 0.058139504309286154, "FinalMeanRMSE": -1}
{"TrainCount": 28, "MeanTrainLoss": 0.055809115036980744, "MeanValidationLoss": 0.058162899306643076, "FinalMeanRMSE": -1}
{"TrainCount": 28, "MeanTrainLoss": 0.0558059364756965, "MeanValidationLoss": 0.05818015689912595, "FinalMeanRMSE": -1}
{"TrainCount": 28, "MeanTrainLoss": 0.05580338094379847, "MeanValidationLoss": 0.05819290013689744, "FinalMeanRMSE": -1}
{"TrainCount": 28, "MeanTrainLoss": 0.05580124900391285, "MeanValidationLoss": 0.05820231671221772, "FinalMeanRMSE": -1}
{"TrainCount": 28, "MeanTrainLoss": 0.05579940726632002, "MeanValidationLoss": 0.058209298516226096, "FinalMeanRMSE": 0.24126603251184928}
{"TrainCount": 29, "MeanTrainLoss": 0.0557156549423065, "MeanValidationLoss": 0.060611491583005335, "FinalMeanRMSE": -1}
{"TrainCount": 29, "MeanTrainLoss": 0.05496415015744063, "MeanValidationLoss": 0.06089583089243914, "FinalMeanRMSE": -1}
{"TrainCount": 29, "MeanTrainLoss": 0.05470132726307922, "MeanValidationLoss": 0.06117126000257692, "FinalMeanRMSE": -1}
{"TrainCount": 29, "MeanTrainLoss": 0.05457800620967902, "MeanValidationLoss": 0.06140828525794143, "FinalMeanRMSE": -1}
{"TrainCount": 29, "MeanTrainLoss": 0.054519601957420415, "MeanValidationLoss": 0.061591825510426794, "FinalMeanRMSE": -1}
{"TrainCount": 29, "MeanTrainLoss": 0.05449163699522615, "MeanValidationLoss": 0.061722788166895554, "FinalMeanRMSE": -1}
{"TrainCount": 29, "MeanTrainLoss": 0.05447707966205131, "MeanValidationLoss": 0.06181106685983891, "FinalMeanRMSE": -1}
{"TrainCount": 29, "MeanTrainLoss": 0.05446816657136366, "MeanValidationLoss": 0.061868192481403794, "FinalMeanRMSE": -1}
{"TrainCount": 29, "MeanTrainLoss": 0.05446167403777826, "MeanValidationLoss": 0.06190404443629629, "FinalMeanRMSE": -1}
{"TrainCount": 29, "MeanTrainLoss": 0.05445639668394205, "MeanValidationLoss": 0.061925955529463186, "FinalMeanRMSE": -1}
{"TrainCount": 29, "MeanTrainLoss": 0.0544518713052701, "MeanValidationLoss": 0.06193870347286452, "FinalMeanRMSE": -1}
{"TrainCount": 29, "MeanTrainLoss": 0.05444787361306473, "MeanValidationLoss": 0.06194558470311735, "FinalMeanRMSE": -1}
{"TrainCount": 29, "MeanTrainLoss": 0.05444429469683651, "MeanValidationLoss": 0.06194880053010001, "FinalMeanRMSE": -1}
{"TrainCount": 29, "MeanTrainLoss": 0.05444107035048378, "MeanValidationLoss": 0.06194974668867039, "FinalMeanRMSE": -1}
{"TrainCount": 29, "MeanTrainLoss": 0.05443814369641895, "MeanValidationLoss": 0.06194930832083649, "FinalMeanRMSE": 0.24889618261329188}
{"TrainCount": 30, "MeanTrainLoss": 0.05874777562120586, "MeanValidationLoss": 0.06107983709945623, "FinalMeanRMSE": -1}
{"TrainCount": 30, "MeanTrainLoss": 0.05842958549851353, "MeanValidationLoss": 0.06125163176143135, "FinalMeanRMSE": -1}
{"TrainCount": 30, "MeanTrainLoss": 0.05832427038440426, "MeanValidationLoss": 0.061346591474711026, "FinalMeanRMSE": -1}
{"TrainCount": 30, "MeanTrainLoss": 0.05826779747182883, "MeanValidationLoss": 0.06141318380832672, "FinalMeanRMSE": -1}
{"TrainCount": 30, "MeanTrainLoss": 0.058233707868358464, "MeanValidationLoss": 0.0614625260928977, "FinalMeanRMSE": -1}
{"TrainCount": 30, "MeanTrainLoss": 0.058211855445672006, "MeanValidationLoss": 0.061499179126396124, "FinalMeanRMSE": -1}
{"TrainCount": 30, "MeanTrainLoss": 0.05819728951720358, "MeanValidationLoss": 0.061526216892389796, "FinalMeanRMSE": -1}
{"TrainCount": 30, "MeanTrainLoss": 0.05818727767293893, "MeanValidationLoss": 0.06154595295906762, "FinalMeanRMSE": -1}
{"TrainCount": 30, "MeanTrainLoss": 0.058180193472834464, "MeanValidationLoss": 0.06156030844668953, "FinalMeanRMSE": -1}
{"TrainCount": 30, "MeanTrainLoss": 0.05817502998900645, "MeanValidationLoss": 0.06157071480076793, "FinalMeanRMSE": -1}
{"TrainCount": 30, "MeanTrainLoss": 0.05817115285153528, "MeanValidationLoss": 0.06157821920800834, "FinalMeanRMSE": -1}
{"TrainCount": 30, "MeanTrainLoss": 0.0581681422238211, "MeanValidationLoss": 0.06158357009335092, "FinalMeanRMSE": -1}
{"TrainCount": 30, "MeanTrainLoss": 0.0581657131464736, "MeanValidationLoss": 0.06158730817779508, "FinalMeanRMSE": -1}
{"TrainCount": 30, "MeanTrainLoss": 0.05816368722510569, "MeanValidationLoss": 0.06158979491224789, "FinalMeanRMSE": -1}
{"TrainCount": 30, "MeanTrainLoss": 0.05816192828046465, "MeanValidationLoss": 0.06159128081433627, "FinalMeanRMSE": 0.24817590525571634}
{"TrainCount": 31, "MeanTrainLoss": 0.055877398184939114, "MeanValidationLoss": 0.06232545659904592, "FinalMeanRMSE": -1}
{"TrainCount": 31, "MeanTrainLoss": 0.055806771710746945, "MeanValidationLoss": 0.062289326380916506, "FinalMeanRMSE": -1}
{"TrainCount": 31, "MeanTrainLoss": 0.05578007788219804, "MeanValidationLoss": 0.06228995501820804, "FinalMeanRMSE": -1}
{"TrainCount": 31, "MeanTrainLoss": 0.05576654270305824, "MeanValidationLoss": 0.062296872642653725, "FinalMeanRMSE": -1}
{"TrainCount": 31, "MeanTrainLoss": 0.055758996841276665, "MeanValidationLoss": 0.06230345573167355, "FinalMeanRMSE": -1}
{"TrainCount": 31, "MeanTrainLoss": 0.055753865043708786, "MeanValidationLoss": 0.062308331766323735, "FinalMeanRMSE": -1}
{"TrainCount": 31, "MeanTrainLoss": 0.05574957804993549, "MeanValidationLoss": 0.06231156984965006, "FinalMeanRMSE": -1}
{"TrainCount": 31, "MeanTrainLoss": 0.05574551898739681, "MeanValidationLoss": 0.06231359392404556, "FinalMeanRMSE": -1}
{"TrainCount": 31, "MeanTrainLoss": 0.055741461262048916, "MeanValidationLoss": 0.06231481560141022, "FinalMeanRMSE": -1}
{"TrainCount": 31, "MeanTrainLoss": 0.055737339956722136, "MeanValidationLoss": 0.062315551204639566, "FinalMeanRMSE": -1}
{"TrainCount": 31, "MeanTrainLoss": 0.05573314198579074, "MeanValidationLoss": 0.06231603026390076, "FinalMeanRMSE": -1}
{"TrainCount": 31, "MeanTrainLoss": 0.055728880431256636, "MeanValidationLoss": 0.06231640593001717, "FinalMeanRMSE": -1}
{"TrainCount": 31, "MeanTrainLoss": 0.055724569444149614, "MeanValidationLoss": 0.06231677841547637, "FinalMeanRMSE": -1}
{"TrainCount": 31, "MeanTrainLoss": 0.05572022141432136, "MeanValidationLoss": 0.062317217607595767, "FinalMeanRMSE": -1}
{"TrainCount": 31, "MeanTrainLoss": 0.0557158552545054, "MeanValidationLoss": 0.0623177661184679, "FinalMeanRMSE": 0.24963526416123846}
{"TrainCount": 32, "MeanTrainLoss": 0.06162696915296461, "MeanValidationLoss": 0.05643711064678396, "FinalMeanRMSE": -1}
{"TrainCount": 32, "MeanTrainLoss": 0.06139463100130158, "MeanValidationLoss": 0.05664056692423159, "FinalMeanRMSE": -1}
{"TrainCount": 32, "MeanTrainLoss": 0.06128133617355874, "MeanValidationLoss": 0.05680912715851227, "FinalMeanRMSE": -1}
{"TrainCount": 32, "MeanTrainLoss": 0.06121303277495739, "MeanValidationLoss": 0.05694449608984021, "FinalMeanRMSE": -1}
{"TrainCount": 32, "MeanTrainLoss": 0.06116854698040122, "MeanValidationLoss": 0.05705420472632254, "FinalMeanRMSE": -1}
{"TrainCount": 32, "MeanTrainLoss": 0.06113826184890633, "MeanValidationLoss": 0.05714391413107084, "FinalMeanRMSE": -1}
{"TrainCount": 32, "MeanTrainLoss": 0.06111710328386239, "MeanValidationLoss": 0.05721746749013146, "FinalMeanRMSE": -1}
{"TrainCount": 32, "MeanTrainLoss": 0.061102023093399516, "MeanValidationLoss": 0.05727763861590038, "FinalMeanRMSE": -1}
{"TrainCount": 32, "MeanTrainLoss": 0.061091044792090765, "MeanValidationLoss": 0.05732664067535042, "FinalMeanRMSE": -1}
{"TrainCount": 32, "MeanTrainLoss": 0.061082847832714664, "MeanValidationLoss": 0.05736636508234663, "FinalMeanRMSE": -1}
{"TrainCount": 32, "MeanTrainLoss": 0.061076554331591135, "MeanValidationLoss": 0.05739844069315519, "FinalMeanRMSE": -1}
{"TrainCount": 32, "MeanTrainLoss": 0.06107157482433641, "MeanValidationLoss": 0.05742432650803141, "FinalMeanRMSE": -1}
{"TrainCount": 32, "MeanTrainLoss": 0.0610675147244696, "MeanValidationLoss": 0.057445289987015584, "FinalMeanRMSE": -1}
{"TrainCount": 32, "MeanTrainLoss": 0.061064100147786626, "MeanValidationLoss": 0.057462380219229385, "FinalMeanRMSE": -1}
{"TrainCount": 32, "MeanTrainLoss": 0.06106114751427849, "MeanValidationLoss": 0.05747645415064227, "FinalMeanRMSE": 0.2397424722153192}
{"TrainCount": 33, "MeanTrainLoss": 0.057115993852358916, "MeanValidationLoss": 0.05515473931158944, "FinalMeanRMSE": -1}
{"TrainCount": 33, "MeanTrainLoss": 0.05683522609372934, "MeanValidationLoss": 0.05510762631458722, "FinalMeanRMSE": -1}
{"TrainCount": 33, "MeanTrainLoss": 0.056687096408171246, "MeanValidationLoss": 0.055126524266974224, "FinalMeanRMSE": -1}
{"TrainCount": 33, "MeanTrainLoss": 0.05661748412115745, "MeanValidationLoss": 0.05517505026767275, "FinalMeanRMSE": -1}
{"TrainCount": 33, "MeanTrainLoss": 0.05658796910095469, "MeanValidationLoss": 0.05522635548698659, "FinalMeanRMSE": -1}
{"TrainCount": 33, "MeanTrainLoss": 0.056576003782566664, "MeanValidationLoss": 0.05526953559835868, "FinalMeanRMSE": -1}
{"TrainCount": 33, "MeanTrainLoss": 0.05657091006174568, "MeanValidationLoss": 0.05530249134097085, "FinalMeanRMSE": -1}
{"TrainCount": 33, "MeanTrainLoss": 0.056568229798400815, "MeanValidationLoss": 0.055326457730013844, "FinalMeanRMSE": -1}
{"TrainCount": 33, "MeanTrainLoss": 0.05656629342354776, "MeanValidationLoss": 0.05534340224008866, "FinalMeanRMSE": -1}
{"TrainCount": 33, "MeanTrainLoss": 0.056564501793549736, "MeanValidationLoss": 0.055355170421280596, "FinalMeanRMSE": -1}
{"TrainCount": 33, "MeanTrainLoss": 0.05656262725057413, "MeanValidationLoss": 0.05536330517370569, "FinalMeanRMSE": -1}
{"TrainCount": 33, "MeanTrainLoss": 0.05656074230061021, "MeanValidationLoss": 0.055368775376946865, "FinalMeanRMSE": -1}
{"TrainCount": 33, "MeanTrainLoss": 0.05655880719278903, "MeanValidationLoss": 0.055372369945396835, "FinalMeanRMSE": -1}
{"TrainCount": 33, "MeanTrainLoss": 0.05655688467587149, "MeanValidationLoss": 0.055374591217617945, "FinalMeanRMSE": -1}
{"TrainCount": 33, "MeanTrainLoss": 0.05655496334296095, "MeanValidationLoss": 0.055375839874104923, "FinalMeanRMSE": 0.23532071713377134}
{"TrainCount": 34, "MeanTrainLoss": 0.0553436270344627, "MeanValidationLoss": 0.06734626729356304, "FinalMeanRMSE": -1}
{"TrainCount": 34, "MeanTrainLoss": 0.05529150112654812, "MeanValidationLoss": 0.06730024003947789, "FinalMeanRMSE": -1}
{"TrainCount": 34, "MeanTrainLoss": 0.05527217512906984, "MeanValidationLoss": 0.0672997452601052, "FinalMeanRMSE": -1}
{"TrainCount": 34, "MeanTrainLoss": 0.05526412746240927, "MeanValidationLoss": 0.06730467437307619, "FinalMeanRMSE": -1}
{"TrainCount": 34, "MeanTrainLoss": 0.055260595569545906, "MeanValidationLoss": 0.06730928882391737, "FinalMeanRMSE": -1}
{"TrainCount": 34, "MeanTrainLoss": 0.05525891540586486, "MeanValidationLoss": 0.06731290941509492, "FinalMeanRMSE": -1}
{"TrainCount": 34, "MeanTrainLoss": 0.05525802719847176, "MeanValidationLoss": 0.06731567985809926, "FinalMeanRMSE": -1}
{"TrainCount": 34, "MeanTrainLoss": 0.05525748194881188, "MeanValidationLoss": 0.06731781419963948, "FinalMeanRMSE": -1}
{"TrainCount": 34, "MeanTrainLoss": 0.05525707950194677, "MeanValidationLoss": 0.06731950676302173, "FinalMeanRMSE": -1}
{"TrainCount": 34, "MeanTrainLoss": 0.055256730422031046, "MeanValidationLoss": 0.06732089934821726, "FinalMeanRMSE": -1}
{"TrainCount": 34, "MeanTrainLoss": 0.05525639996856682, "MeanValidationLoss": 0.06732208853039033, "FinalMeanRMSE": -1}
{"TrainCount": 34, "MeanTrainLoss": 0.05525607514635537, "MeanValidationLoss": 0.06732314386277435, "FinalMeanRMSE": -1}
{"TrainCount": 34, "MeanTrainLoss": 0.05525573825304823, "MeanValidationLoss": 0.06732409232385653, "FinalMeanRMSE": -1}
{"TrainCount": 34, "MeanTrainLoss": 0.055255383975053016, "MeanValidationLoss": 0.06732495819861965, "FinalMeanRMSE": -1}
{"TrainCount": 34, "MeanTrainLoss": 0.055255011908074685, "MeanValidationLoss": 0.06732576238344432, "FinalMeanRMSE": 0.2594720861616039}
{"TrainCount": 35, "MeanTrainLoss": 0.055555273375520305, "MeanValidationLoss": 0.057377109411119044, "FinalMeanRMSE": -1}
{"TrainCount": 35, "MeanTrainLoss": 0.05546377250974662, "MeanValidationLoss": 0.05736500649959191, "FinalMeanRMSE": -1}
{"TrainCount": 35, "MeanTrainLoss": 0.055408530051452444, "MeanValidationLoss": 0.057349774172936366, "FinalMeanRMSE": -1}
{"TrainCount": 35, "MeanTrainLoss": 0.05537446531185245, "MeanValidationLoss": 0.057339272793682144, "FinalMeanRMSE": -1}
{"TrainCount": 35, "MeanTrainLoss": 0.055353714046122014, "MeanValidationLoss": 0.057333876517997394, "FinalMeanRMSE": -1}
{"TrainCount": 35, "MeanTrainLoss": 0.055341103067800004, "MeanValidationLoss": 0.05733253644115623, "FinalMeanRMSE": -1}
{"TrainCount": 35, "MeanTrainLoss": 0.055333490030290526, "MeanValidationLoss": 0.057334004548089255, "FinalMeanRMSE": -1}
{"TrainCount": 35, "MeanTrainLoss": 0.055328936098407513, "MeanValidationLoss": 0.057337165135761786, "FinalMeanRMSE": -1}
{"TrainCount": 35, "MeanTrainLoss": 0.05532624147175829, "MeanValidationLoss": 0.057341163014543464, "FinalMeanRMSE": -1}
{"TrainCount": 35, "MeanTrainLoss": 0.05532465555430372, "MeanValidationLoss": 0.05734540804706771, "FinalMeanRMSE": -1}
{"TrainCount": 35, "MeanTrainLoss": 0.05532371977850852, "MeanValidationLoss": 0.05734953001655381, "FinalMeanRMSE": -1}
{"TrainCount": 35, "MeanTrainLoss": 0.05532315065120828, "MeanValidationLoss": 0.057353328784991955, "FinalMeanRMSE": -1}
{"TrainCount": 35, "MeanTrainLoss": 0.055322772584198994, "MeanValidationLoss": 0.057356707152278946, "FinalMeanRMSE": -1}
{"TrainCount": 35, "MeanTrainLoss": 0.05532248891975688, "MeanValidationLoss": 0.0573596411395347, "FinalMeanRMSE": -1}
{"TrainCount": 35, "MeanTrainLoss": 0.055322237826626874, "MeanValidationLoss": 0.05736215138572386, "FinalMeanRMSE": 0.23950396788902803}
{"TrainCount": 36, "MeanTrainLoss": 0.060131839235204196, "MeanValidationLoss": 0.064504977949071, "FinalMeanRMSE": -1}
{"TrainCount": 36, "MeanTrainLoss": 0.05997967488363013, "MeanValidationLoss": 0.06438591374186342, "FinalMeanRMSE": -1}
{"TrainCount": 36, "MeanTrainLoss": 0.05991416537487118, "MeanValidationLoss": 0.06431786874872807, "FinalMeanRMSE": -1}
{"TrainCount": 36, "MeanTrainLoss": 0.05987312930015822, "MeanValidationLoss": 0.06428225040006363, "FinalMeanRMSE": -1}
{"TrainCount": 36, "MeanTrainLoss": 0.059848518116174414, "MeanValidationLoss": 0.06426553610680083, "FinalMeanRMSE": -1}
{"TrainCount": 36, "MeanTrainLoss": 0.059833491839568584, "MeanValidationLoss": 0.06425914509753329, "FinalMeanRMSE": -1}
{"TrainCount": 36, "MeanTrainLoss": 0.05982391461873009, "MeanValidationLoss": 0.06425806523571784, "FinalMeanRMSE": -1}
{"TrainCount": 36, "MeanTrainLoss": 0.05981747468579525, "MeanValidationLoss": 0.0642594840238005, "FinalMeanRMSE": -1}
{"TrainCount": 36, "MeanTrainLoss": 0.059812894716658654, "MeanValidationLoss": 0.06426186833842, "FinalMeanRMSE": -1}
{"TrainCount": 36, "MeanTrainLoss": 0.059809454057129695, "MeanValidationLoss": 0.06426441712406938, "FinalMeanRMSE": -1}
{"TrainCount": 36, "MeanTrainLoss": 0.0598067200730149, "MeanValidationLoss": 0.06426676195275886, "FinalMeanRMSE": -1}
{"TrainCount": 36, "MeanTrainLoss": 0.05980444119638994, "MeanValidationLoss": 0.06426874260479848, "FinalMeanRMSE": -1}
{"TrainCount": 36, "MeanTrainLoss": 0.059802466384966405, "MeanValidationLoss": 0.06427032088254302, "FinalMeanRMSE": -1}
{"TrainCount": 36, "MeanTrainLoss": 0.05980069902430569, "MeanValidationLoss": 0.06427152018983358, "FinalMeanRMSE": -1}
{"TrainCount": 36, "MeanTrainLoss": 0.059799078358569666, "MeanValidationLoss": 0.06427238626078158, "FinalMeanRMSE": 0.2535199939504324}
{"TrainCount": 37, "MeanTrainLoss": 0.059695036651996464, "MeanValidationLoss": 0.06717773037358732, "FinalMeanRMSE": -1}
{"TrainCount": 37, "MeanTrainLoss": 0.05965427853740179, "MeanValidationLoss": 0.06717728028981074, "FinalMeanRMSE": -1}
{"TrainCount": 37, "MeanTrainLoss": 0.05963362036989285, "MeanValidationLoss": 0.06718137232259302, "FinalMeanRMSE": -1}
{"TrainCount": 37, "MeanTrainLoss": 0.05962066289324027, "MeanValidationLoss": 0.0671863564926197, "FinalMeanRMSE": -1}
{"TrainCount": 37, "MeanTrainLoss": 0.05961199740950878, "MeanValidationLoss": 0.06719096716740289, "FinalMeanRMSE": -1}
{"TrainCount": 37, "MeanTrainLoss": 0.05960587389194048, "MeanValidationLoss": 0.06719478030799102, "FinalMeanRMSE": -1}
{"TrainCount": 37, "MeanTrainLoss": 0.05960133379468551, "MeanValidationLoss": 0.06719770344774043, "FinalMeanRMSE": -1}
{"TrainCount": 37, "MeanTrainLoss": 0.05959780600208502, "MeanValidationLoss": 0.0671998044148474, "FinalMeanRMSE": -1}
{"TrainCount": 37, "MeanTrainLoss": 0.059594948589801786, "MeanValidationLoss": 0.06720120341702222, "FinalMeanRMSE": -1}
{"TrainCount": 37, "MeanTrainLoss": 0.05959254921628879, "MeanValidationLoss": 0.06720202199320285, "FinalMeanRMSE": -1}
{"TrainCount": 37, "MeanTrainLoss": 0.05959047044699008, "MeanValidationLoss": 0.06720237677610917, "FinalMeanRMSE": -1}
{"TrainCount": 37, "MeanTrainLoss": 0.05958862258837773, "MeanValidationLoss": 0.06720236152066965, "FinalMeanRMSE": -1}
{"TrainCount": 37, "MeanTrainLoss": 0.05958694746861091, "MeanValidationLoss": 0.06720206610622255, "FinalMeanRMSE": -1}
{"TrainCount": 37, "MeanTrainLoss": 0.05958539597116984, "MeanValidationLoss": 0.06720155155452597, "FinalMeanRMSE": -1}
{"TrainCount": 37, "MeanTrainLoss": 0.059583946489370786, "MeanValidationLoss": 0.06720087366978442, "FinalMeanRMSE": 0.2592313134373331}
{"TrainCount": 38, "MeanTrainLoss": 0.05881498684932123, "MeanValidationLoss": 0.06169832900337789, "FinalMeanRMSE": -1}
{"TrainCount": 38, "MeanTrainLoss": 0.05880344568628882, "MeanValidationLoss": 0.06164408727795228, "FinalMeanRMSE": -1}
{"TrainCount": 38, "MeanTrainLoss": 0.05879656621477572, "MeanValidationLoss": 0.06161035665835457, "FinalMeanRMSE": -1}
{"TrainCount": 38, "MeanTrainLoss": 0.05879253775850081, "MeanValidationLoss": 0.06158851429648783, "FinalMeanRMSE": -1}
{"TrainCount": 38, "MeanTrainLoss": 0.05878936688827055, "MeanValidationLoss": 0.06157385742013482, "FinalMeanRMSE": -1}
{"TrainCount": 38, "MeanTrainLoss": 0.05878653129416716, "MeanValidationLoss": 0.06156375631690025, "FinalMeanRMSE": -1}
{"TrainCount": 38, "MeanTrainLoss": 0.05878388653037425, "MeanValidationLoss": 0.06155664435234563, "FinalMeanRMSE": -1}
{"TrainCount": 38, "MeanTrainLoss": 0.0587813841538721, "MeanValidationLoss": 0.06155153496683329, "FinalMeanRMSE": -1}
{"TrainCount": 38, "MeanTrainLoss": 0.05877899815173496, "MeanValidationLoss": 0.06154777944601815, "FinalMeanRMSE": -1}
{"TrainCount": 38, "MeanTrainLoss": 0.05877671478383856, "MeanValidationLoss": 0.061544958202318215, "FinalMeanRMSE": -1}
{"TrainCount": 38, "MeanTrainLoss": 0.058774515145937296, "MeanValidationLoss": 0.06154278952671194, "FinalMeanRMSE": -1}
{"TrainCount": 38, "MeanTrainLoss": 0.058772386153216116, "MeanValidationLoss": 0.061541071739690055, "FinalMeanRMSE": -1}
{"TrainCount": 38, "MeanTrainLoss": 0.05877032425133494, "MeanValidationLoss": 0.061539670388246405, "FinalMeanRMSE": -1}
{"TrainCount": 38, "MeanTrainLoss": 0.058768326291960465, "MeanValidationLoss": 0.06153848086451662, "FinalMeanRMSE": -1}
{"TrainCount": 38, "MeanTrainLoss": 0.05876638646990802, "MeanValidationLoss": 0.0615374394960102, "FinalMeanRMSE": 0.2480674094319037}
{"TrainCount": 39, "MeanTrainLoss": 0.06073150990737809, "MeanValidationLoss": 0.04808713749094037, "FinalMeanRMSE": -1}
{"TrainCount": 39, "MeanTrainLoss": 0.06059811709598563, "MeanValidationLoss": 0.04821402212384798, "FinalMeanRMSE": -1}
{"TrainCount": 39, "MeanTrainLoss": 0.06053508001725792, "MeanValidationLoss": 0.04833201965268819, "FinalMeanRMSE": -1}
{"TrainCount": 39, "MeanTrainLoss": 0.06049894816973657, "MeanValidationLoss": 0.04842791671969362, "FinalMeanRMSE": -1}
{"TrainCount": 39, "MeanTrainLoss": 0.06047695077299158, "MeanValidationLoss": 0.048502736545090026, "FinalMeanRMSE": -1}
{"TrainCount": 39, "MeanTrainLoss": 0.0604632030672954, "MeanValidationLoss": 0.048559735204369604, "FinalMeanRMSE": -1}
{"TrainCount": 39, "MeanTrainLoss": 0.06045440744280359, "MeanValidationLoss": 0.04860246220136582, "FinalMeanRMSE": -1}
{"TrainCount": 39, "MeanTrainLoss": 0.06044857596471848, "MeanValidationLoss": 0.048634102047348575, "FinalMeanRMSE": -1}
{"TrainCount": 39, "MeanTrainLoss": 0.06044459732613344, "MeanValidationLoss": 0.04865733063873709, "FinalMeanRMSE": -1}
{"TrainCount": 39, "MeanTrainLoss": 0.0604417282103122, "MeanValidationLoss": 0.04867429404334307, "FinalMeanRMSE": -1}
{"TrainCount": 39, "MeanTrainLoss": 0.060439556851355054, "MeanValidationLoss": 0.04868663694999403, "FinalMeanRMSE": -1}
{"TrainCount": 39, "MeanTrainLoss": 0.060437856306289804, "MeanValidationLoss": 0.04869560482952025, "FinalMeanRMSE": -1}
{"TrainCount": 39, "MeanTrainLoss": 0.060436447704089555, "MeanValidationLoss": 0.04870207435974814, "FinalMeanRMSE": -1}
{"TrainCount": 39, "MeanTrainLoss": 0.06043524286527743, "MeanValidationLoss": 0.048706696274816476, "FinalMeanRMSE": -1}
{"TrainCount": 39, "MeanTrainLoss": 0.06043417863119608, "MeanValidationLoss": 0.04870996448165745, "FinalMeanRMSE": 0.22070334264780594}
{"TrainCount": 40, "MeanTrainLoss": 0.06286858998495957, "MeanValidationLoss": 0.06091255885723345, "FinalMeanRMSE": -1}
{"TrainCount": 40, "MeanTrainLoss": 0.06266240127584487, "MeanValidationLoss": 0.06101862611705357, "FinalMeanRMSE": -1}
{"TrainCount": 40, "MeanTrainLoss": 0.06256354825706774, "MeanValidationLoss": 0.06108050117059812, "FinalMeanRMSE": -1}
{"TrainCount": 40, "MeanTrainLoss": 0.0625063673917818, "MeanValidationLoss": 0.06112111767791534, "FinalMeanRMSE": -1}
{"TrainCount": 40, "MeanTrainLoss": 0.06246995651858977, "MeanValidationLoss": 0.06115105836209372, "FinalMeanRMSE": -1}
{"TrainCount": 40, "MeanTrainLoss": 0.06244521102800223, "MeanValidationLoss": 0.06117522126058337, "FinalMeanRMSE": -1}
{"TrainCount": 40, "MeanTrainLoss": 0.062427523949137136, "MeanValidationLoss": 0.06119589934860938, "FinalMeanRMSE": -1}
{"TrainCount": 40, "MeanTrainLoss": 0.0624143118431285, "MeanValidationLoss": 0.061214248303549434, "FinalMeanRMSE": -1}
{"TrainCount": 40, "MeanTrainLoss": 0.06240401588294698, "MeanValidationLoss": 0.06123083381127212, "FinalMeanRMSE": -1}
{"TrainCount": 40, "MeanTrainLoss": 0.06239568690458933, "MeanValidationLoss": 0.06124594541379286, "FinalMeanRMSE": -1}
{"TrainCount": 40, "MeanTrainLoss": 0.06238872141102721, "MeanValidationLoss": 0.06125975602040717, "FinalMeanRMSE": -1}
{"TrainCount": 40, "MeanTrainLoss": 0.06238268738277114, "MeanValidationLoss": 0.061272406719775296, "FinalMeanRMSE": -1}
{"TrainCount": 40, "MeanTrainLoss": 0.06237730840613559, "MeanValidationLoss": 0.061284012383961195, "FinalMeanRMSE": -1}
{"TrainCount": 40, "MeanTrainLoss": 0.06237240118541937, "MeanValidationLoss": 0.06129466918342739, "FinalMeanRMSE": -1}
{"TrainCount": 40, "MeanTrainLoss": 0.062367840716436904, "MeanValidationLoss": 0.06130446993909583, "FinalMeanRMSE": 0.24759739626243085}
{"TrainCount": 41, "MeanTrainLoss": 0.06213792726283765, "MeanValidationLoss": 0.06539933501948259, "FinalMeanRMSE": -1}
{"TrainCount": 41, "MeanTrainLoss": 0.06187733422026379, "MeanValidationLoss": 0.06545940818622666, "FinalMeanRMSE": -1}
{"TrainCount": 41, "MeanTrainLoss": 0.06178198635350657, "MeanValidationLoss": 0.0655535776114737, "FinalMeanRMSE": -1}
{"TrainCount": 41, "MeanTrainLoss": 0.06173287405995012, "MeanValidationLoss": 0.06562024787239154, "FinalMeanRMSE": -1}
{"TrainCount": 41, "MeanTrainLoss": 0.06170114516529418, "MeanValidationLoss": 0.06566311963393559, "FinalMeanRMSE": -1}
{"TrainCount": 41, "MeanTrainLoss": 0.06167676009749638, "MeanValidationLoss": 0.0656921118177623, "FinalMeanRMSE": -1}
{"TrainCount": 41, "MeanTrainLoss": 0.06165589289810821, "MeanValidationLoss": 0.06571398574036992, "FinalMeanRMSE": -1}
{"TrainCount": 41, "MeanTrainLoss": 0.06163701238750501, "MeanValidationLoss": 0.06573253925516134, "FinalMeanRMSE": -1}
{"TrainCount": 41, "MeanTrainLoss": 0.061619363895809375, "MeanValidationLoss": 0.06574975071544292, "FinalMeanRMSE": -1}
{"TrainCount": 41, "MeanTrainLoss": 0.061602561357822126, "MeanValidationLoss": 0.06576666789913929, "FinalMeanRMSE": -1}
{"TrainCount": 41, "MeanTrainLoss": 0.06158638973044985, "MeanValidationLoss": 0.0657838051311437, "FinalMeanRMSE": -1}
{"TrainCount": 41, "MeanTrainLoss": 0.06157071990821198, "MeanValidationLoss": 0.06580142587167144, "FinalMeanRMSE": -1}
{"TrainCount": 41, "MeanTrainLoss": 0.0615554841533872, "MeanValidationLoss": 0.06581965554238732, "FinalMeanRMSE": -1}
{"TrainCount": 41, "MeanTrainLoss": 0.0615406476018083, "MeanValidationLoss": 0.0658385775193444, "FinalMeanRMSE": -1}
{"TrainCount": 41, "MeanTrainLoss": 0.06152620900223273, "MeanValidationLoss": 0.06585821860541928, "FinalMeanRMSE": 0.25662856501244585}
{"TrainCount": 42, "MeanTrainLoss": 0.06234300828914569, "MeanValidationLoss": 0.06799856684673791, "FinalMeanRMSE": -1}
{"TrainCount": 42, "MeanTrainLoss": 0.06206737508566384, "MeanValidationLoss": 0.06773794862045639, "FinalMeanRMSE": -1}
{"TrainCount": 42, "MeanTrainLoss": 0.061987199815235906, "MeanValidationLoss": 0.06764207977330548, "FinalMeanRMSE": -1}
{"TrainCount": 42, "MeanTrainLoss": 0.06195425156710481, "MeanValidationLoss": 0.0675937859662648, "FinalMeanRMSE": -1}
{"TrainCount": 42, "MeanTrainLoss": 0.06193741633205979, "MeanValidationLoss": 0.06756431249708965, "FinalMeanRMSE": -1}
{"TrainCount": 42, "MeanTrainLoss": 0.0619273363660672, "MeanValidationLoss": 0.06754383855852587, "FinalMeanRMSE": -1}
{"TrainCount": 42, "MeanTrainLoss": 0.06192063248180295, "MeanValidationLoss": 0.06752819396641063, "FinalMeanRMSE": -1}
{"TrainCount": 42, "MeanTrainLoss": 0.0619158070983212, "MeanValidationLoss": 0.06751534916546154, "FinalMeanRMSE": -1}
{"TrainCount": 42, "MeanTrainLoss": 0.061912098703603216, "MeanValidationLoss": 0.06750421697038343, "FinalMeanRMSE": -1}
{"TrainCount": 42, "MeanTrainLoss": 0.0619090882416665, "MeanValidationLoss": 0.06749419773789658, "FinalMeanRMSE": -1}
{"TrainCount": 42, "MeanTrainLoss": 0.06190653141039507, "MeanValidationLoss": 0.06748493041457801, "FinalMeanRMSE": -1}
{"TrainCount": 42, "MeanTrainLoss": 0.06190427533755111, "MeanValidationLoss": 0.06747620432883844, "FinalMeanRMSE": -1}
{"TrainCount": 42, "MeanTrainLoss": 0.061902222239606466, "MeanValidationLoss": 0.06746787183928764, "FinalMeanRMSE": -1}
{"TrainCount": 42, "MeanTrainLoss": 0.06190031372281379, "MeanValidationLoss": 0.06745983411868413, "FinalMeanRMSE": -1}
{"TrainCount": 42, "MeanTrainLoss": 0.061898505297377275, "MeanValidationLoss": 0.06745202205646997, "FinalMeanRMSE": 0.2597152722391863}
{"TrainCount": 43, "MeanTrainLoss": 0.0648341880847211, "MeanValidationLoss": 0.06405759123207509, "FinalMeanRMSE": -1}
{"TrainCount": 43, "MeanTrainLoss": 0.06476695784207048, "MeanValidationLoss": 0.06412422438633852, "FinalMeanRMSE": -1}
{"TrainCount": 43, "MeanTrainLoss": 0.06470695734594974, "MeanValidationLoss": 0.06419240220867355, "FinalMeanRMSE": -1}
{"TrainCount": 43, "MeanTrainLoss": 0.06467156574643891, "MeanValidationLoss": 0.06425681247793395, "FinalMeanRMSE": -1}
{"TrainCount": 43, "MeanTrainLoss": 0.06464824814106769, "MeanValidationLoss": 0.0643138772454755, "FinalMeanRMSE": -1}
{"TrainCount": 43, "MeanTrainLoss": 0.06463287382518651, "MeanValidationLoss": 0.06436248252104068, "FinalMeanRMSE": -1}
{"TrainCount": 43, "MeanTrainLoss": 0.0646225828891513, "MeanValidationLoss": 0.06440278408171117, "FinalMeanRMSE": -1}
{"TrainCount": 43, "MeanTrainLoss": 0.06461550506595451, "MeanValidationLoss": 0.06443554458433184, "FinalMeanRMSE": -1}
{"TrainCount": 43, "MeanTrainLoss": 0.06461042765228228, "MeanValidationLoss": 0.0644617613790364, "FinalMeanRMSE": -1}
{"TrainCount": 43, "MeanTrainLoss": 0.06460658069771369, "MeanValidationLoss": 0.0644824909067702, "FinalMeanRMSE": -1}
{"TrainCount": 43, "MeanTrainLoss": 0.06460348008578765, "MeanValidationLoss": 0.0644987371974978, "FinalMeanRMSE": -1}
{"TrainCount": 43, "MeanTrainLoss": 0.0646008362144346, "MeanValidationLoss": 0.0645113849006165, "FinalMeanRMSE": -1}
{"TrainCount": 43, "MeanTrainLoss": 0.0645984690993225, "MeanValidationLoss": 0.06452118151489346, "FinalMeanRMSE": -1}
{"TrainCount": 43, "MeanTrainLoss": 0.0645962764020167, "MeanValidationLoss": 0.06452874239833875, "FinalMeanRMSE": -1}
{"TrainCount": 43, "MeanTrainLoss": 0.06459419534923473, "MeanValidationLoss": 0.06453457311994729, "FinalMeanRMSE": 0.25403655850337004}
{"TrainCount": 44, "MeanTrainLoss": 0.06491337394430524, "MeanValidationLoss": 0.06574183503929046, "FinalMeanRMSE": -1}
{"TrainCount": 44, "MeanTrainLoss": 0.06482058583270936, "MeanValidationLoss": 0.06586676925676942, "FinalMeanRMSE": -1}
{"TrainCount": 44, "MeanTrainLoss": 0.06479018902494794, "MeanValidationLoss": 0.0659524922000303, "FinalMeanRMSE": -1}
{"TrainCount": 44, "MeanTrainLoss": 0.06477366885968618, "MeanValidationLoss": 0.06601180848171855, "FinalMeanRMSE": -1}
{"TrainCount": 44, "MeanTrainLoss": 0.06476190030574798, "MeanValidationLoss": 0.06605310534209781, "FinalMeanRMSE": -1}
{"TrainCount": 44, "MeanTrainLoss": 0.0647519297684942, "MeanValidationLoss": 0.06608199463746267, "FinalMeanRMSE": -1}
{"TrainCount": 44, "MeanTrainLoss": 0.06474260203895114, "MeanValidationLoss": 0.06610227517121843, "FinalMeanRMSE": -1}
{"TrainCount": 44, "MeanTrainLoss": 0.06473343606506075, "MeanValidationLoss": 0.06611657456460177, "FinalMeanRMSE": -1}
{"TrainCount": 44, "MeanTrainLoss": 0.06472423103593644, "MeanValidationLoss": 0.06612669714969345, "FinalMeanRMSE": -1}
{"TrainCount": 44, "MeanTrainLoss": 0.06471489406767346, "MeanValidationLoss": 0.06613387557061491, "FinalMeanRMSE": -1}
{"TrainCount": 44, "MeanTrainLoss": 0.06470538812024253, "MeanValidationLoss": 0.06613897631494568, "FinalMeanRMSE": -1}
{"TrainCount": 44, "MeanTrainLoss": 0.06469570276283082, "MeanValidationLoss": 0.06614259283530678, "FinalMeanRMSE": -1}
{"TrainCount": 44, "MeanTrainLoss": 0.06468583017587662, "MeanValidationLoss": 0.06614514934512811, "FinalMeanRMSE": -1}
{"TrainCount": 44, "MeanTrainLoss": 0.06467577204817818, "MeanValidationLoss": 0.06614693905357645, "FinalMeanRMSE": -1}
{"TrainCount": 44, "MeanTrainLoss": 0.06466551706904457, "MeanValidationLoss": 0.06614815757575213, "FinalMeanRMSE": 0.2571928428549375}
{"TrainCount": 45, "MeanTrainLoss": 0.062271874234789894, "MeanValidationLoss": 0.06202718549351979, "FinalMeanRMSE": -1}
{"TrainCount": 45, "MeanTrainLoss": 0.06222347646951675, "MeanValidationLoss": 0.06204902049805169, "FinalMeanRMSE": -1}
{"TrainCount": 45, "MeanTrainLoss": 0.062212568038985845, "MeanValidationLoss": 0.062056676983662525, "FinalMeanRMSE": -1}
{"TrainCount": 45, "MeanTrainLoss": 0.062205448959554946, "MeanValidationLoss": 0.06206230915292969, "FinalMeanRMSE": -1}
{"TrainCount": 45, "MeanTrainLoss": 0.06219916194677353, "MeanValidationLoss": 0.06206781666907335, "FinalMeanRMSE": -1}
{"TrainCount": 45, "MeanTrainLoss": 0.06219329625368118, "MeanValidationLoss": 0.06207350440814365, "FinalMeanRMSE": -1}
{"TrainCount": 45, "MeanTrainLoss": 0.06218775861320042, "MeanValidationLoss": 0.06207936656338438, "FinalMeanRMSE": -1}
{"TrainCount": 45, "MeanTrainLoss": 0.06218252180587678, "MeanValidationLoss": 0.06208533738182062, "FinalMeanRMSE": -1}
{"TrainCount": 45, "MeanTrainLoss": 0.062177552254427046, "MeanValidationLoss": 0.06209136964086134, "FinalMeanRMSE": -1}
{"TrainCount": 45, "MeanTrainLoss": 0.062172817431745075, "MeanValidationLoss": 0.06209741961904788, "FinalMeanRMSE": -1}
{"TrainCount": 45, "MeanTrainLoss": 0.06216829518477122, "MeanValidationLoss": 0.06210343689153393, "FinalMeanRMSE": -1}
{"TrainCount": 45, "MeanTrainLoss": 0.062164016309238616, "MeanValidationLoss": 0.06210918218580563, "FinalMeanRMSE": -1}
{"TrainCount": 45, "MeanTrainLoss": 0.06215990287917001, "MeanValidationLoss": 0.062115251121343376, "FinalMeanRMSE": -1}
{"TrainCount": 45, "MeanTrainLoss": 0.06215592460972922, "MeanValidationLoss": 0.062121101620374916, "FinalMeanRMSE": -1}
{"TrainCount": 45, "MeanTrainLoss": 0.06215221816585177, "MeanValidationLoss": 0.06212672992558739, "FinalMeanRMSE": 0.2492523403668011}
{"TrainCount": 46, "MeanTrainLoss": 0.06702111100147605, "MeanValidationLoss": 0.06648452360086933, "FinalMeanRMSE": -1}
{"TrainCount": 46, "MeanTrainLoss": 0.0665273439587872, "MeanValidationLoss": 0.06659922806444687, "FinalMeanRMSE": -1}
{"TrainCount": 46, "MeanTrainLoss": 0.0663935329416058, "MeanValidationLoss": 0.06664325243507893, "FinalMeanRMSE": -1}
{"TrainCount": 46, "MeanTrainLoss": 0.06632830037327615, "MeanValidationLoss": 0.06667100704331111, "FinalMeanRMSE": -1}
{"TrainCount": 46, "MeanTrainLoss": 0.06629362810638165, "MeanValidationLoss": 0.06669527234610992, "FinalMeanRMSE": -1}
{"TrainCount": 46, "MeanTrainLoss": 0.0662750785112609, "MeanValidationLoss": 0.06671755634952753, "FinalMeanRMSE": -1}
{"TrainCount": 46, "MeanTrainLoss": 0.06626525387367373, "MeanValidationLoss": 0.0667373696422167, "FinalMeanRMSE": -1}
{"TrainCount": 46, "MeanTrainLoss": 0.06626014015414747, "MeanValidationLoss": 0.06675431012765726, "FinalMeanRMSE": -1}
{"TrainCount": 46, "MeanTrainLoss": 0.06625752871852532, "MeanValidationLoss": 0.06676834038215927, "FinalMeanRMSE": -1}
{"TrainCount": 46, "MeanTrainLoss": 0.06625621082051078, "MeanValidationLoss": 0.06677969705238725, "FinalMeanRMSE": -1}
{"TrainCount": 46, "MeanTrainLoss": 0.0662555277034156, "MeanValidationLoss": 0.06678873072124826, "FinalMeanRMSE": -1}
{"TrainCount": 46, "MeanTrainLoss": 0.06625512537206336, "MeanValidationLoss": 0.06679582583016175, "FinalMeanRMSE": -1}
{"TrainCount": 46, "MeanTrainLoss": 0.06625482444268567, "MeanValidationLoss": 0.06680135048904529, "FinalMeanRMSE": -1}
{"TrainCount": 46, "MeanTrainLoss": 0.06625453475328522, "MeanValidationLoss": 0.06680561271215919, "FinalMeanRMSE": -1}
{"TrainCount": 46, "MeanTrainLoss": 0.066254211928033, "MeanValidationLoss": 0.06680886835969964, "FinalMeanRMSE": 0.25847411758673716}
{"TrainCount": 47, "MeanTrainLoss": 0.06074195619375645, "MeanValidationLoss": 0.06561245043308307, "FinalMeanRMSE": -1}
{"TrainCount": 47, "MeanTrainLoss": 0.060683722685548905, "MeanValidationLoss": 0.06571335900585536, "FinalMeanRMSE": -1}
{"TrainCount": 47, "MeanTrainLoss": 0.060694854338944976, "MeanValidationLoss": 0.06572670545800459, "FinalMeanRMSE": -1}
{"TrainCount": 47, "MeanTrainLoss": 0.06069215454790296, "MeanValidationLoss": 0.06572226942264796, "FinalMeanRMSE": -1}
{"TrainCount": 47, "MeanTrainLoss": 0.060685113781048745, "MeanValidationLoss": 0.0657137572404496, "FinalMeanRMSE": -1}
{"TrainCount": 47, "MeanTrainLoss": 0.06067701671237172, "MeanValidationLoss": 0.06570515128919202, "FinalMeanRMSE": -1}
{"TrainCount": 47, "MeanTrainLoss": 0.060669010467968694, "MeanValidationLoss": 0.06569759633678657, "FinalMeanRMSE": -1}
{"TrainCount": 47, "MeanTrainLoss": 0.060661449867602885, "MeanValidationLoss": 0.06569135826919494, "FinalMeanRMSE": -1}
{"TrainCount": 47, "MeanTrainLoss": 0.060654454314957536, "MeanValidationLoss": 0.0656863366097127, "FinalMeanRMSE": -1}
{"TrainCount": 47, "MeanTrainLoss": 0.060647961374308626, "MeanValidationLoss": 0.06568222028067988, "FinalMeanRMSE": -1}
{"TrainCount": 47, "MeanTrainLoss": 0.06064187671522658, "MeanValidationLoss": 0.06567889083696907, "FinalMeanRMSE": -1}
{"TrainCount": 47, "MeanTrainLoss": 0.060636154648121554, "MeanValidationLoss": 0.06567623305991505, "FinalMeanRMSE": -1}
{"TrainCount": 47, "MeanTrainLoss": 0.0606307579695726, "MeanValidationLoss": 0.06567413463891401, "FinalMeanRMSE": -1}
{"TrainCount": 47, "MeanTrainLoss": 0.06062565044812731, "MeanValidationLoss": 0.06567251382984667, "FinalMeanRMSE": -1}
{"TrainCount": 47, "MeanTrainLoss": 0.060620806595236346, "MeanValidationLoss": 0.06567131147382946, "FinalMeanRMSE": 0.2562641432429575}
{"TrainCount": 48, "MeanTrainLoss": 0.06177532588216392, "MeanValidationLoss": 0.057515834917200255, "FinalMeanRMSE": -1}
{"TrainCount": 48, "MeanTrainLoss": 0.06178768374251597, "MeanValidationLoss": 0.05758487437440459, "FinalMeanRMSE": -1}
{"TrainCount": 48, "MeanTrainLoss": 0.06179582688844565, "MeanValidationLoss": 0.057564582622628604, "FinalMeanRMSE": -1}
{"TrainCount": 48, "MeanTrainLoss": 0.0617847532372583, "MeanValidationLoss": 0.05754168955688803, "FinalMeanRMSE": -1}
{"TrainCount": 48, "MeanTrainLoss": 0.06177338269172293, "MeanValidationLoss": 0.05752293428039958, "FinalMeanRMSE": -1}
{"TrainCount": 48, "MeanTrainLoss": 0.06176262298090891, "MeanValidationLoss": 0.057508187968167146, "FinalMeanRMSE": -1}
{"TrainCount": 48, "MeanTrainLoss": 0.06175220915765473, "MeanValidationLoss": 0.057496761006337625, "FinalMeanRMSE": -1}
{"TrainCount": 48, "MeanTrainLoss": 0.06174193181549058, "MeanValidationLoss": 0.05748800468495768, "FinalMeanRMSE": -1}
{"TrainCount": 48, "MeanTrainLoss": 0.061731672874002746, "MeanValidationLoss": 0.05748136027416273, "FinalMeanRMSE": -1}
{"TrainCount": 48, "MeanTrainLoss": 0.06172134930437261, "MeanValidationLoss": 0.05747638922980708, "FinalMeanRMSE": -1}
{"TrainCount": 48, "MeanTrainLoss": 0.06171091674177936, "MeanValidationLoss": 0.057472758377209686, "FinalMeanRMSE": -1}
{"TrainCount": 48, "MeanTrainLoss": 0.061700343690586815, "MeanValidationLoss": 0.05747019520767054, "FinalMeanRMSE": -1}
{"TrainCount": 48, "MeanTrainLoss": 0.061689610903461777, "MeanValidationLoss": 0.05746849726068328, "FinalMeanRMSE": -1}
{"TrainCount": 48, "MeanTrainLoss": 0.06167870274547375, "MeanValidationLoss": 0.05746750176971794, "FinalMeanRMSE": -1}
{"TrainCount": 48, "MeanTrainLoss": 0.061667615829995186, "MeanValidationLoss": 0.05746709338874898, "FinalMeanRMSE": 0.23972295277595018}
{"TrainCount": 49, "MeanTrainLoss": 0.062042844381469946, "MeanValidationLoss": 0.06264528675230942, "FinalMeanRMSE": -1}
{"TrainCount": 49, "MeanTrainLoss": 0.06164533584736861, "MeanValidationLoss": 0.06287123168134964, "FinalMeanRMSE": -1}
{"TrainCount": 49, "MeanTrainLoss": 0.06153653069184377, "MeanValidationLoss": 0.06298768356700853, "FinalMeanRMSE": -1}
{"TrainCount": 49, "MeanTrainLoss": 0.06148095967677923, "MeanValidationLoss": 0.06307726689329037, "FinalMeanRMSE": -1}
{"TrainCount": 49, "MeanTrainLoss": 0.061453275841016036, "MeanValidationLoss": 0.06314288058205147, "FinalMeanRMSE": -1}
{"TrainCount": 49, "MeanTrainLoss": 0.061438957085976235, "MeanValidationLoss": 0.06318883081047522, "FinalMeanRMSE": -1}
{"TrainCount": 49, "MeanTrainLoss": 0.06143089446883935, "MeanValidationLoss": 0.0632204069309152, "FinalMeanRMSE": -1}
{"TrainCount": 49, "MeanTrainLoss": 0.06142579999107581, "MeanValidationLoss": 0.06324209862878558, "FinalMeanRMSE": -1}
{"TrainCount": 49, "MeanTrainLoss": 0.061422165196675524, "MeanValidationLoss": 0.06325720810476755, "FinalMeanRMSE": -1}
{"TrainCount": 49, "MeanTrainLoss": 0.06141928938718943, "MeanValidationLoss": 0.06326799839735031, "FinalMeanRMSE": -1}
{"TrainCount": 49, "MeanTrainLoss": 0.06141684628449953, "MeanValidationLoss": 0.06327598434307671, "FinalMeanRMSE": -1}
{"TrainCount": 49, "MeanTrainLoss": 0.06141466750548436, "MeanValidationLoss": 0.06328214235560742, "FinalMeanRMSE": -1}
{"TrainCount": 49, "MeanTrainLoss": 0.06141266278349436, "MeanValidationLoss": 0.06328710551895847, "FinalMeanRMSE": -1}
{"TrainCount": 49, "MeanTrainLoss": 0.061410783632443504, "MeanValidationLoss": 0.06329127220232363, "FinalMeanRMSE": -1}
{"TrainCount": 49, "MeanTrainLoss": 0.06140900494960638, "MeanValidationLoss": 0.06329490347749236, "FinalMeanRMSE": 0.2515847847842357}
{"TrainCount": 50, "MeanTrainLoss": 0.06514340334317902, "MeanValidationLoss": 0.06566121781568582, "FinalMeanRMSE": -1}
{"TrainCount": 50, "MeanTrainLoss": 0.06485658500230673, "MeanValidationLoss": 0.0656460101830314, "FinalMeanRMSE": -1}
{"TrainCount": 50, "MeanTrainLoss": 0.06476432739785223, "MeanValidationLoss": 0.06567009406806397, "FinalMeanRMSE": -1}
{"TrainCount": 50, "MeanTrainLoss": 0.06471643608176347, "MeanValidationLoss": 0.06569802308948632, "FinalMeanRMSE": -1}
{"TrainCount": 50, "MeanTrainLoss": 0.06468790916330887, "MeanValidationLoss": 0.0657230498656588, "FinalMeanRMSE": -1}
{"TrainCount": 50, "MeanTrainLoss": 0.06466921655969186, "MeanValidationLoss": 0.06574389213255667, "FinalMeanRMSE": -1}
{"TrainCount": 50, "MeanTrainLoss": 0.06465584310618314, "MeanValidationLoss": 0.06576069539938217, "FinalMeanRMSE": -1}
{"TrainCount": 50, "MeanTrainLoss": 0.06464553861455484, "MeanValidationLoss": 0.06577403525001982, "FinalMeanRMSE": -1}
{"TrainCount": 50, "MeanTrainLoss": 0.06463706713508476, "MeanValidationLoss": 0.06578457578379884, "FinalMeanRMSE": -1}
{"TrainCount": 50, "MeanTrainLoss": 0.06462974789919275, "MeanValidationLoss": 0.06579290763435201, "FinalMeanRMSE": -1}
{"TrainCount": 50, "MeanTrainLoss": 0.06462319900817944, "MeanValidationLoss": 0.06579952956604482, "FinalMeanRMSE": -1}
{"TrainCount": 50, "MeanTrainLoss": 0.06461719886371584, "MeanValidationLoss": 0.06580484656357018, "FinalMeanRMSE": -1}
{"TrainCount": 50, "MeanTrainLoss": 0.06461161894328667, "MeanValidationLoss": 0.06580918199486202, "FinalMeanRMSE": -1}
{"TrainCount": 50, "MeanTrainLoss": 0.06460637418609677, "MeanValidationLoss": 0.06581278826691146, "FinalMeanRMSE": -1}
{"TrainCount": 50, "MeanTrainLoss": 0.06460140634215239, "MeanValidationLoss": 0.06581585871273296, "FinalMeanRMSE": 0.2565460177282424}
{"TrainCount": 51, "MeanTrainLoss": 0.05981949618884495, "MeanValidationLoss": 0.06006680701460157, "FinalMeanRMSE": -1}
{"TrainCount": 51, "MeanTrainLoss": 0.05978492397637594, "MeanValidationLoss": 0.06013232903821128, "FinalMeanRMSE": -1}
{"TrainCount": 51, "MeanTrainLoss": 0.05976934270489784, "MeanValidationLoss": 0.060185969386781966, "FinalMeanRMSE": -1}
{"TrainCount": 51, "MeanTrainLoss": 0.05975859168739546, "MeanValidationLoss": 0.06022725024393626, "FinalMeanRMSE": -1}
{"TrainCount": 51, "MeanTrainLoss": 0.0597509622219063, "MeanValidationLoss": 0.06025927432945796, "FinalMeanRMSE": -1}
{"TrainCount": 51, "MeanTrainLoss": 0.05974524756982213, "MeanValidationLoss": 0.060284290782042914, "FinalMeanRMSE": -1}
{"TrainCount": 51, "MeanTrainLoss": 0.05974069312924431, "MeanValidationLoss": 0.06030393157686506, "FinalMeanRMSE": -1}
{"TrainCount": 51, "MeanTrainLoss": 0.059736857201371875, "MeanValidationLoss": 0.06031945773533413, "FinalMeanRMSE": -1}
{"TrainCount": 51, "MeanTrainLoss": 0.05973348476347469, "MeanValidationLoss": 0.060331842729023526, "FinalMeanRMSE": -1}
{"TrainCount": 51, "MeanTrainLoss": 0.05973043238123258, "MeanValidationLoss": 0.060341845410210745, "FinalMeanRMSE": -1}
{"TrainCount": 51, "MeanTrainLoss": 0.05972760434661593, "MeanValidationLoss": 0.060350060803549634, "FinalMeanRMSE": -1}
{"TrainCount": 51, "MeanTrainLoss": 0.05972495531042417, "MeanValidationLoss": 0.0603569456083434, "FinalMeanRMSE": -1}
{"TrainCount": 51, "MeanTrainLoss": 0.059722456605661486, "MeanValidationLoss": 0.060362822243145535, "FinalMeanRMSE": -1}
{"TrainCount": 51, "MeanTrainLoss": 0.05972008724297796, "MeanValidationLoss": 0.06036796339920589, "FinalMeanRMSE": -1}
{"TrainCount": 51, "MeanTrainLoss": 0.059717820563486644, "MeanValidationLoss": 0.060372557427201955, "FinalMeanRMSE": 0.24570827853967536}
{"TrainCount": 52, "MeanTrainLoss": 0.06283548564621896, "MeanValidationLoss": 0.07188529126409791, "FinalMeanRMSE": -1}
{"TrainCount": 52, "MeanTrainLoss": 0.06268204946183797, "MeanValidationLoss": 0.07207743494514048, "FinalMeanRMSE": -1}
{"TrainCount": 52, "MeanTrainLoss": 0.06264155962024674, "MeanValidationLoss": 0.07218544768896537, "FinalMeanRMSE": -1}
{"TrainCount": 52, "MeanTrainLoss": 0.06261720835711017, "MeanValidationLoss": 0.07225149906004256, "FinalMeanRMSE": -1}
{"TrainCount": 52, "MeanTrainLoss": 0.06259975875868942, "MeanValidationLoss": 0.07229469720794265, "FinalMeanRMSE": -1}
{"TrainCount": 52, "MeanTrainLoss": 0.06258645343283813, "MeanValidationLoss": 0.07232426060230983, "FinalMeanRMSE": -1}
{"TrainCount": 52, "MeanTrainLoss": 0.06257588269584106, "MeanValidationLoss": 0.07234494428434263, "FinalMeanRMSE": -1}
{"TrainCount": 52, "MeanTrainLoss": 0.06256719774594813, "MeanValidationLoss": 0.07235948130106315, "FinalMeanRMSE": -1}
{"TrainCount": 52, "MeanTrainLoss": 0.06255987450254685, "MeanValidationLoss": 0.07236955038927219, "FinalMeanRMSE": -1}
{"TrainCount": 52, "MeanTrainLoss": 0.06255352028617353, "MeanValidationLoss": 0.0723761992789062, "FinalMeanRMSE": -1}
{"TrainCount": 52, "MeanTrainLoss": 0.0625477810813622, "MeanValidationLoss": 0.07238023681433452, "FinalMeanRMSE": -1}
{"TrainCount": 52, "MeanTrainLoss": 0.06254254947557594, "MeanValidationLoss": 0.07238230151668233, "FinalMeanRMSE": -1}
{"TrainCount": 52, "MeanTrainLoss": 0.06253768334334547, "MeanValidationLoss": 0.07238283657874817, "FinalMeanRMSE": -1}
{"TrainCount": 52, "MeanTrainLoss": 0.06253310050250906, "MeanValidationLoss": 0.0723822015812594, "FinalMeanRMSE": -1}
{"TrainCount": 52, "MeanTrainLoss": 0.06252880134817326, "MeanValidationLoss": 0.07238076695180007, "FinalMeanRMSE": 0.26903674086143387}
